{
  "categories": [
    { "id": "no1", "name": "Con người & Gia đình", "color": "blue", "wordCount": 47},
    { "id": "no2", "name": "Đồ vật & Quần áo", "color": "teal", "wordCount": 42},
    { "id": "no3", "name": "Đồ ăn & Thức uống", "color": "orange", "wordCount": 30},
    { "id": "no4", "name": "Nơi chốn & Di chuyển", "color": "green", "wordCount": 45},
    { "id": "no5", "name": "Động vật", "color": "pink", "wordCount": 12},
    { "id": "no6", "name": "Thời gian & Lịch", "color": "indigo", "wordCount": 40},
	{ "id": "no7", "name": "Trường học & Công việc", "color": "purple", "wordCount": 40},    
    { "id": "no8", "name": "Mô tả (Tính từ & Trạng từ)", "color": "amber", "wordCount": 72},
	{ "id": "no9", "name": "Hành động (Động từ)", "color": "red", "wordCount": 94},
    { "id": "no10", "name": "Từ vựng cơ bản", "color": "grey", "wordCount": 178}	    
  ],
  "flashcards": [
    { "id": 1,  "english": "A", "vietnamese": "Một (trước phụ âm)", "phonetic": "/ə/", "categoryId": "no10", "image": "a", "level": "A1"},
    { "id": 2,  "english": "An", "vietnamese": "Một (trước nguyên âm)", "phonetic": "/ən/", "categoryId": "no10", "image": "an", "level": "A1"},
    { "id": 3,  "english": "About", "vietnamese": "Về, khoảng", "phonetic": "/əˈbaʊt/", "categoryId": "no10", "image": "about", "level": "A1"},
    { "id": 4,  "english": "Above", "vietnamese": "Ở trên", "phonetic": "/əˈbʌv/", "categoryId": "no10", "image": "above", "level": "A1"},
    { "id": 5,  "english": "Across", "vietnamese": "Băng qua", "phonetic": "/əˈkrɒs/", "categoryId": "no4", "image": "across", "level": "A1"},
    { "id": 6,  "english": "Action", "vietnamese": "Hành động", "phonetic": "/ˈækʃn/", "categoryId": "no10", "image": "action", "level": "A1"},
    { "id": 7,  "english": "Activity", "vietnamese": "Hoạt động", "phonetic": "/ækˈtɪvəti/", "categoryId": "no10", "image": "activity", "level": "A1"},
    { "id": 8,  "english": "Actor", "vietnamese": "Diễn viên (nam)", "phonetic": "/ˈæktər/", "categoryId": "no1", "image": "actor", "level": "A1"},
    { "id": 9,  "english": "Actress", "vietnamese": "Diễn viên (nữ)", "phonetic": "/ˈæktrəs/", "categoryId": "no1", "image": "actress", "level": "A1"},
    { "id": 10, "english": "Add", "vietnamese": "Thêm vào", "phonetic": "/æd/", "categoryId": "no9", "image": "add", "level": "A1"},
    { "id": 11, "english": "Address", "vietnamese": "Địa chỉ", "phonetic": "/əˈdres/", "categoryId": "no4", "image": "address", "level": "A1"},
    { "id": 12, "english": "Adult", "vietnamese": "Người lớn", "phonetic": "/ˈædʌlt/", "categoryId": "no1", "image": "adult", "level": "A1"},
    { "id": 13, "english": "Advice", "vietnamese": "Lời khuyên", "phonetic": "/ədˈvaɪs/", "categoryId": "no10", "image": "advice", "level": "A1"},
    { "id": 14, "english": "Afraid", "vietnamese": "Sợ hãi", "phonetic": "/əˈfreɪd/", "categoryId": "no8", "image": "afraid", "level": "A1"},
    { "id": 15, "english": "After", "vietnamese": "Sau khi", "phonetic": "/ˈɑːftər/", "categoryId": "no10", "image": "after", "level": "A1"},
    { "id": 16, "english": "Afternoon", "vietnamese": "Buổi chiều", "phonetic": "/ˌɑːftəˈnuːn/", "categoryId": "no6", "image": "afternoon", "level": "A1"},
    { "id": 17, "english": "Again", "vietnamese": "Lần nữa", "phonetic": "/əˈɡen/", "categoryId": "no10", "image": "again", "level": "A1"},
    { "id": 18, "english": "Age", "vietnamese": "Tuổi", "phonetic": "/eɪdʒ/", "categoryId": "no10", "image": "age", "level": "A1"},
    { "id": 19, "english": "Ago", "vietnamese": "Trước đây", "phonetic": "/əˈɡəʊ/", "categoryId": "no6", "image": "ago", "level": "A1"},
    { "id": 20, "english": "Agree", "vietnamese": "Đồng ý", "phonetic": "/əˈɡriː/", "categoryId": "no9", "image": "agree", "level": "A1"},
    { "id": 21, "english": "Air", "vietnamese": "Không khí", "phonetic": "/eər/", "categoryId": "no10", "image": "air", "level": "A1"},
    { "id": 22, "english": "Airport", "vietnamese": "Sân bay", "phonetic": "/ˈeəpɔːt/", "categoryId": "no4", "image": "airport", "level": "A1"},
    { "id": 23, "english": "Also", "vietnamese": "Cũng vậy", "phonetic": "/ˈɔːlsəʊ/", "categoryId": "no10", "image": "also", "level": "A1"},
    { "id": 24, "english": "Always", "vietnamese": "Luôn luôn", "phonetic": "/ˈɔːlweɪz/", "categoryId": "no6", "image": "always", "level": "A1"},
    { "id": 25, "english": "Amazing", "vietnamese": "Tuyệt vời", "phonetic": "/əˈmeɪzɪŋ/", "categoryId": "no8", "image": "amazing", "level": "A1"},
    { "id": 26, "english": "And", "vietnamese": "Và", "phonetic": "/ənd/", "categoryId": "no10", "image": "and", "level": "A1"},
    { "id": 27, "english": "Angry", "vietnamese": "Tức giận", "phonetic": "/ˈæŋɡri/", "categoryId": "no8", "image": "angry", "level": "A1"},
    { "id": 28, "english": "Animal", "vietnamese": "Động vật", "phonetic": "/ˈænɪml/", "categoryId": "no5", "image": "animal", "level": "A1"},
    { "id": 29, "english": "Another", "vietnamese": "Một cái khác", "phonetic": "/əˈnʌðər/", "categoryId": "no10", "image": "another", "level": "A1"},
    { "id": 30, "english": "Answer", "vietnamese": "Trả lời", "phonetic": "/ˈɑːnsər/", "categoryId": "no9", "image": "answer", "level": "A1"},
    { "id": 31, "english": "Anyone", "vietnamese": "Bất cứ ai", "phonetic": "/ˈeniwʌn/", "categoryId": "no1", "image": "anyone", "level": "A1"},
    { "id": 32, "english": "Anything", "vietnamese": "Bất cứ điều gì", "phonetic": "/ˈeniθɪŋ/", "categoryId": "no10", "image": "anything", "level": "A1"},
    { "id": 33, "english": "Apartment", "vietnamese": "Căn hộ", "phonetic": "/əˈpɑːtmənt/", "categoryId": "no4", "image": "apartment", "level": "A1"},
    { "id": 34, "english": "Apple", "vietnamese": "Quả táo", "phonetic": "/ˈæpl/", "categoryId": "no3", "image": "apple", "level": "A1"},
    { "id": 35, "english": "April", "vietnamese": "Tháng Tư", "phonetic": "/ˈeɪprəl/", "categoryId": "no6", "image": "april", "level": "A1"},
    { "id": 36, "english": "Area", "vietnamese": "Khu vực", "phonetic": "/ˈeəriə/", "categoryId": "no4", "image": "area", "level": "A1"},
    { "id": 37, "english": "Arm", "vietnamese": "Cánh tay", "phonetic": "/ɑːm/", "categoryId": "no10", "image": "arm", "level": "A1"},
    { "id": 38, "english": "Around", "vietnamese": "Xung quanh", "phonetic": "/əˈraʊnd/", "categoryId": "no10", "image": "around", "level": "A1"},
    { "id": 39, "english": "Arrive", "vietnamese": "Đến nơi", "phonetic": "/əˈraɪv/", "categoryId": "no9", "image": "arrive", "level": "A1"},
    { "id": 40, "english": "Art", "vietnamese": "Nghệ thuật", "phonetic": "/ɑːt/", "categoryId": "no7", "image": "art", "level": "A1"},
    { "id": 41, "english": "Article", "vietnamese": "Bài báo", "phonetic": "/ˈɑːtɪkl/", "categoryId": "no7", "image": "article", "level": "A1"},
    { "id": 42, "english": "Artist", "vietnamese": "Nghệ sĩ", "phonetic": "/ˈɑːtɪst/", "categoryId": "no1", "image": "artist", "level": "A1"},
    { "id": 43, "english": "As", "vietnamese": "Như là", "phonetic": "/æz/", "categoryId": "no10", "image": "as", "level": "A1"},
    { "id": 44, "english": "Ask", "vietnamese": "Hỏi", "phonetic": "/ɑːsk/", "categoryId": "no9", "image": "ask", "level": "A1"},
    { "id": 45, "english": "At", "vietnamese": "Tại", "phonetic": "/æt/", "categoryId": "no10", "image": "at", "level": "A1"},
    { "id": 46, "english": "August", "vietnamese": "Tháng Tám", "phonetic": "/ˈɔːɡəst/", "categoryId": "no6", "image": "august", "level": "A1"},
    { "id": 47, "english": "Aunt", "vietnamese": "Cô, dì", "phonetic": "/ɑːnt/", "categoryId": "no1", "image": "aunt", "level": "A1"},
    { "id": 48, "english": "Autumn", "vietnamese": "Mùa thu", "phonetic": "/ˈɔːtəm/", "categoryId": "no6", "image": "autumn", "level": "A1"},
    { "id": 49, "english": "Away", "vietnamese": "Xa", "phonetic": "/əˈweɪ/", "categoryId": "no10", "image": "away", "level": "A1"},
    { "id": 50, "english": "Awesome", "vietnamese": "Tuyệt vời", "phonetic": "/ˈɔːsəm/", "categoryId": "no8", "image": "awesome", "level": "A1"},
    { "id": 51, "english": "Baby", "vietnamese": "Em bé", "phonetic": "/ˈbeɪbi/", "categoryId": "no1", "image": "baby", "level": "A1"},
    { "id": 52, "english": "Back", "vietnamese": "Lưng, phía sau", "phonetic": "/bæk/", "categoryId": "no10", "image": "back", "level": "A1"},
    { "id": 53, "english": "Bad", "vietnamese": "Tồi tệ", "phonetic": "/bæd/", "categoryId": "no8", "image": "bad", "level": "A1"},
    { "id": 54, "english": "Bag", "vietnamese": "Cái túi", "phonetic": "/bæɡ/", "categoryId": "no2", "image": "bag", "level": "A1"},
    { "id": 55, "english": "Ball", "vietnamese": "Quả bóng", "phonetic": "/bɔːl/", "categoryId": "no2", "image": "ball", "level": "A1"},
    { "id": 56, "english": "Banana", "vietnamese": "Quả chuối", "phonetic": "/bəˈnɑːnə/", "categoryId": "no3", "image": "banana", "level": "A1"},
    { "id": 57, "english": "Band", "vietnamese": "Ban nhạc", "phonetic": "/bænd/", "categoryId": "no7", "image": "band", "level": "A1"},
    { "id": 58, "english": "Bank", "vietnamese": "Ngân hàng", "phonetic": "/bæŋk/", "categoryId": "no4", "image": "bank", "level": "A1"},
    { "id": 59, "english": "Bar", "vietnamese": "Quán bar", "phonetic": "/bɑːr/", "categoryId": "no4", "image": "bar", "level": "A1"},
    { "id": 60, "english": "Baseball", "vietnamese": "Bóng chày", "phonetic": "/ˈbeɪsbɔːl/", "categoryId": "no10", "image": "baseball", "level": "A1"},
    { "id": 61, "english": "Basketball", "vietnamese": "Bóng rổ", "phonetic": "/ˈbɑːskɪtbɔːl/", "categoryId": "no10", "image": "basketball", "level": "A1"},
    { "id": 62, "english": "Bath", "vietnamese": "Bồn tắm", "phonetic": "/bɑːθ/", "categoryId": "no2", "image": "bath", "level": "A1"},
    { "id": 63, "english": "Bathroom", "vietnamese": "Phòng tắm", "phonetic": "/ˈbɑːθruːm/", "categoryId": "no4", "image": "bathroom", "level": "A1"},
    { "id": 64, "english": "Be", "vietnamese": "Thì, là, ở", "phonetic": "/biː/", "categoryId": "no9", "image": "be", "level": "A1"},
    { "id": 65, "english": "Beach", "vietnamese": "Bãi biển", "phonetic": "/biːtʃ/", "categoryId": "no4", "image": "beach", "level": "A1"},
    { "id": 66, "english": "Beautiful", "vietnamese": "Xinh đẹp", "phonetic": "/ˈbjuːtɪfl/", "categoryId": "no8", "image": "beautiful", "level": "A1"},
    { "id": 67, "english": "Because", "vietnamese": "Bởi vì", "phonetic": "/bɪˈkɒz/", "categoryId": "no10", "image": "because", "level": "A1"},
    { "id": 68, "english": "Become", "vietnamese": "Trở nên", "phonetic": "/bɪˈkʌm/", "categoryId": "no9", "image": "become", "level": "A1"},
    { "id": 69, "english": "Bed", "vietnamese": "Cái giường", "phonetic": "/bed/", "categoryId": "no2", "image": "bed", "level": "A1"},
    { "id": 70, "english": "Bedroom", "vietnamese": "Phòng ngủ", "phonetic": "/ˈbedruːm/", "categoryId": "no4", "image": "bedroom", "level": "A1"},
    { "id": 71, "english": "Beer", "vietnamese": "Bia", "phonetic": "/bɪər/", "categoryId": "no3", "image": "beer", "level": "A1"},
    { "id": 72, "english": "Before", "vietnamese": "Trước khi", "phonetic": "/bɪˈfɔːr/", "categoryId": "no10", "image": "before", "level": "A1"},
    { "id": 73, "english": "Begin", "vietnamese": "Bắt đầu", "phonetic": "/bɪˈɡɪn/", "categoryId": "no9", "image": "begin", "level": "A1"},
    { "id": 74, "english": "Beginning", "vietnamese": "Sự bắt đầu", "phonetic": "/bɪˈɡɪnɪŋ/", "categoryId": "no10", "image": "beginning", "level": "A1"},
    { "id": 75, "english": "Behind", "vietnamese": "Phía sau", "phonetic": "/bɪˈhaɪnd/", "categoryId": "no10", "image": "behind", "level": "A1"},
    { "id": 76, "english": "Believe", "vietnamese": "Tin tưởng", "phonetic": "/bɪˈliːv/", "categoryId": "no9", "image": "believe", "level": "A1"},
    { "id": 77, "english": "Below", "vietnamese": "Bên dưới", "phonetic": "/bɪˈləʊ/", "categoryId": "no10", "image": "below", "level": "A1"},
    { "id": 78, "english": "Best", "vietnamese": "Tốt nhất", "phonetic": "/best/", "categoryId": "no8", "image": "best", "level": "A1"},
    { "id": 79, "english": "Better", "vietnamese": "Tốt hơn", "phonetic": "/ˈbetər/", "categoryId": "no8", "image": "better", "level": "A1"},
    { "id": 80, "english": "Between", "vietnamese": "Ở giữa", "phonetic": "/bɪˈtwiːn/", "categoryId": "no10", "image": "between", "level": "A1"},
    { "id": 81, "english": "Bicycle", "vietnamese": "Xe đạp", "phonetic": "/ˈbaɪsɪkl/", "categoryId": "no2", "image": "bicycle", "level": "A1"},
    { "id": 82, "english": "Big", "vietnamese": "To, lớn", "phonetic": "/bɪɡ/", "categoryId": "no8", "image": "big", "level": "A1"},
    { "id": 83, "english": "Bike", "vietnamese": "Xe đạp", "phonetic": "/baɪk/", "categoryId": "no2", "image": "bike", "level": "A1"},
    { "id": 84, "english": "Bill", "vietnamese": "Hóa đơn", "phonetic": "/bɪl/", "categoryId": "no10", "image": "bill", "level": "A1"},
    { "id": 85, "english": "Bird", "vietnamese": "Con chim", "phonetic": "/bɜːd/", "categoryId": "no5", "image": "https://upload.wikimedia.org/wikipedia/commons/5/50/Bird_chim_se.png", "level": "A1"},
    { "id": 86, "english": "Birthday", "vietnamese": "Sinh nhật", "phonetic": "/ˈbɜːθdeɪ/", "categoryId": "no6", "image": "birthday", "level": "A1"},
    { "id": 87, "english": "Black", "vietnamese": "Màu đen", "phonetic": "/blæk/", "categoryId": "no10", "image": "black", "level": "A1"},
    { "id": 88, "english": "Blog", "vietnamese": "Trang blog", "phonetic": "/blɒɡ/", "categoryId": "no7", "image": "blog", "level": "A1"},
    { "id": 89, "english": "Blond", "vietnamese": "Vàng hoe (tóc)", "phonetic": "/blɒnd/", "categoryId": "no8", "image": "blond", "level": "A1"},
    { "id": 90, "english": "Blue", "vietnamese": "Màu xanh dương", "phonetic": "/bluː/", "categoryId": "no10", "image": "blue", "level": "A1"},
    { "id": 91, "english": "Boat", "vietnamese": "Thuyền", "phonetic": "/bəʊt/", "categoryId": "no4", "image": "boat", "level": "A1"},
    { "id": 92, "english": "Body", "vietnamese": "Cơ thể", "phonetic": "/ˈbɒdi/", "categoryId": "no10", "image": "body", "level": "A1"},
    { "id": 93, "english": "Book", "vietnamese": "Sách", "phonetic": "/bʊk/", "categoryId": "no2", "image": "book", "level": "A1"},
    { "id": 94, "english": "Boot", "vietnamese": "Giày ống", "phonetic": "/buːt/", "categoryId": "no2", "image": "boot", "level": "A1"},
    { "id": 95, "english": "Bored", "vietnamese": "Buồn chán", "phonetic": "/bɔːd/", "categoryId": "no8", "image": "bored", "level": "A1"},
    { "id": 96, "english": "Boring", "vietnamese": "Tẻ nhạt", "phonetic": "/ˈbɔːrɪŋ/", "categoryId": "no8", "image": "boring", "level": "A1"},
    { "id": 97, "english": "Born", "vietnamese": "Được sinh ra", "phonetic": "/bɔːn/", "categoryId": "no9", "image": "born", "level": "A1"},
    { "id": 98, "english": "Both", "vietnamese": "Cả hai", "phonetic": "/bəʊθ/", "categoryId": "no10", "image": "both", "level": "A1"},
    { "id": 99, "english": "Bottle", "vietnamese": "Cái chai", "phonetic": "/ˈbɒtl/", "categoryId": "no2", "image": "bottle", "level": "A1"},
    { "id": 100, "english": "Box", "vietnamese": "Cái hộp", "phonetic": "/bɒks/", "categoryId": "no2", "image": "box", "level": "A1"},
    { "id": 101, "english": "Boy", "vietnamese": "Cậu bé", "phonetic": "/bɔɪ/", "categoryId": "no1", "image": "boy", "level": "A1"},
    { "id": 102, "english": "Boyfriend", "vietnamese": "Bạn trai", "phonetic": "/ˈbɔɪfrend/", "categoryId": "no1", "image": "boyfriend", "level": "A1"},
    { "id": 103, "english": "Bread", "vietnamese": "Bánh mì", "phonetic": "/bred/", "categoryId": "no3", "image": "bread", "level": "A1"},
    { "id": 104, "english": "Break", "vietnamese": "Làm vỡ", "phonetic": "/breɪk/", "categoryId": "no9", "image": "break", "level": "A1"},
    { "id": 105, "english": "Breakfast", "vietnamese": "Bữa sáng", "phonetic": "/ˈbrekfəst/", "categoryId": "no3", "image": "breakfast", "level": "A1"},
    { "id": 106, "english": "Bring", "vietnamese": "Mang đến", "phonetic": "/brɪŋ/", "categoryId": "no9", "image": "bring", "level": "A1"},
    { "id": 107, "english": "Brother", "vietnamese": "Anh/em trai", "phonetic": "/ˈbrʌðər/", "categoryId": "no1", "image": "brother", "level": "A1"},
    { "id": 108, "english": "Brown", "vietnamese": "Màu nâu", "phonetic": "/braʊn/", "categoryId": "no10", "image": "brown", "level": "A1"},
    { "id": 109, "english": "Build", "vietnamese": "Xây dựng", "phonetic": "/bɪld/", "categoryId": "no9", "image": "build", "level": "A1"},
    { "id": 110, "english": "Building", "vietnamese": "Tòa nhà", "phonetic": "/ˈbɪldɪŋ/", "categoryId": "no4", "image": "building", "level": "A1"},
    { "id": 111, "english": "Bus", "vietnamese": "Xe buýt", "phonetic": "/bʌs/", "categoryId": "no4", "image": "bus", "level": "A1"},
    { "id": 112, "english": "Business", "vietnamese": "Kinh doanh", "phonetic": "/ˈbɪznəs/", "categoryId": "no7", "image": "business", "level": "A1"},
    { "id": 113, "english": "Busy", "vietnamese": "Bận rộn", "phonetic": "/ˈbɪzi/", "categoryId": "no8", "image": "busy", "level": "A1"},
    { "id": 114, "english": "But", "vietnamese": "Nhưng", "phonetic": "/bʌt/", "categoryId": "no10", "image": "but", "level": "A1"},
    { "id": 115, "english": "Butter", "vietnamese": "Bơ", "phonetic": "/ˈbʌtər/", "categoryId": "no3", "image": "butter", "level": "A1"},
    { "id": 116, "english": "Buy", "vietnamese": "Mua", "phonetic": "/baɪ/", "categoryId": "no9", "image": "buy", "level": "A1"},
    { "id": 117, "english": "By", "vietnamese": "Bởi, bằng", "phonetic": "/baɪ/", "categoryId": "no10", "image": "by", "level": "A1"},
    { "id": 118, "english": "Bye", "vietnamese": "Tạm biệt", "phonetic": "/baɪ/", "categoryId": "no10", "image": "bye", "level": "A1"},
    { "id": 119, "english": "Cafe", "vietnamese": "Quán cà phê", "phonetic": "/ˈkæfeɪ/", "categoryId": "no4", "image": "cafe", "level": "A1"},
    { "id": 120, "english": "Cake", "vietnamese": "Bánh ngọt", "phonetic": "/keɪk/", "categoryId": "no3", "image": "cake", "level": "A1"},
    { "id": 121, "english": "Call", "vietnamese": "Gọi", "phonetic": "/kɔːl/", "categoryId": "no9", "image": "call", "level": "A1"},
    { "id": 122, "english": "Camera", "vietnamese": "Máy ảnh", "phonetic": "/ˈkæmərə/", "categoryId": "no2", "image": "camera", "level": "A1"},
    { "id": 123, "english": "Can", "vietnamese": "Có thể", "phonetic": "/kæn/", "categoryId": "no9", "image": "can", "level": "A1"},
    { "id": 124, "english": "Cannot", "vietnamese": "Không thể", "phonetic": "/ˈkænɒt/", "categoryId": "no9", "image": "cannot", "level": "A1"},
    { "id": 125, "english": "Capital", "vietnamese": "Thủ đô, chữ hoa", "phonetic": "/ˈkæpɪtl/", "categoryId": "no4", "image": "capital", "level": "A1"},
    { "id": 126, "english": "Car", "vietnamese": "Xe hơi", "phonetic": "/kɑːr/", "categoryId": "no4", "image": "car", "level": "A1"},
    { "id": 127, "english": "Card", "vietnamese": "Thẻ", "phonetic": "/kɑːd/", "categoryId": "no2", "image": "card", "level": "A1"},
    { "id": 128, "english": "Career", "vietnamese": "Sự nghiệp", "phonetic": "/kəˈrɪər/", "categoryId": "no7", "image": "career", "level": "A1"},
    { "id": 129, "english": "Carrot", "vietnamese": "Cà rốt", "phonetic": "/ˈkærət/", "categoryId": "no3", "image": "carrot", "level": "A1"},
    { "id": 130, "english": "Carry", "vietnamese": "Mang", "phonetic": "/ˈkæri/", "categoryId": "no9", "image": "carry", "level": "A1"},
    { "id": 131, "english": "Cat", "vietnamese": "Con mèo", "phonetic": "/kæt/", "categoryId": "no5", "image": "https://upload.wikimedia.org/wikipedia/commons/f/fe/Cat_meo_muop.png", "level": "A1"},
    { "id": 132, "english": "CD", "vietnamese": "Đĩa CD", "phonetic": "/ˌsiːˈdiː/", "categoryId": "no2", "image": "cd", "level": "A1"},
    { "id": 133, "english": "Cent", "vietnamese": "Xu (tiền)", "phonetic": "/sent/", "categoryId": "no10", "image": "cent", "level": "A1"},
    { "id": 134, "english": "Center", "vietnamese": "Trung tâm", "phonetic": "/ˈsentər/", "categoryId": "no4", "image": "center", "level": "A1"},
    { "id": 135, "english": "Chair", "vietnamese": "Cái ghế", "phonetic": "/tʃeər/", "categoryId": "no2", "image": "chair", "level": "A1"},
    { "id": 136, "english": "Change", "vietnamese": "Thay đổi", "phonetic": "/tʃeɪndʒ/", "categoryId": "no9", "image": "change", "level": "A1"},
    { "id": 137, "english": "Chart", "vietnamese": "Biểu đồ", "phonetic": "/tʃɑːt/", "categoryId": "no7", "image": "chart", "level": "A1"},
    { "id": 138, "english": "Cheap", "vietnamese": "Rẻ", "phonetic": "/tʃiːp/", "categoryId": "no8", "image": "cheap", "level": "A1"},
    { "id": 139, "english": "Check", "vietnamese": "Kiểm tra", "phonetic": "/tʃek/", "categoryId": "no9", "image": "check", "level": "A1"},
    { "id": 140, "english": "Cheese", "vietnamese": "Phô mai", "phonetic": "/tʃiːz/", "categoryId": "no3", "image": "cheese", "level": "A1"},
    { "id": 141, "english": "Chicken", "vietnamese": "Con gà", "phonetic": "/ˈtʃɪkɪn/", "categoryId": "no5", "image": "https://upload.wikimedia.org/wikipedia/commons/4/41/Chicken_ga_choi.png", "level": "A1"},
    { "id": 142, "english": "Child", "vietnamese": "Đứa trẻ", "phonetic": "/tʃaɪld/", "categoryId": "no1", "image": "child", "level": "A1"},
    { "id": 143, "english": "Chocolate", "vietnamese": "Sô cô la", "phonetic": "/ˈtʃɒklət/", "categoryId": "no3", "image": "chocolate", "level": "A1"},
    { "id": 144, "english": "Choose", "vietnamese": "Lựa chọn", "phonetic": "/tʃuːz/", "categoryId": "no9", "image": "choose", "level": "A1"},
    { "id": 145, "english": "City", "vietnamese": "Thành phố", "phonetic": "/ˈsɪti/", "categoryId": "no4", "image": "city", "level": "A1"},
    { "id": 146, "english": "Class", "vietnamese": "Lớp học", "phonetic": "/klɑːs/", "categoryId": "no7", "image": "class", "level": "A1"},
    { "id": 147, "english": "Classroom", "vietnamese": "Phòng học", "phonetic": "/ˈklɑːsruːm/", "categoryId": "no7", "image": "classroom", "level": "A1"},
    { "id": 148, "english": "Clean", "vietnamese": "Sạch sẽ, dọn dẹp", "phonetic": "/kliːn/", "categoryId": "no9", "image": "clean", "level": "A1"},
    { "id": 149, "english": "Climb", "vietnamese": "Leo, trèo", "phonetic": "/klaɪm/", "categoryId": "no9", "image": "climb", "level": "A1"},
    { "id": 150, "english": "Clock", "vietnamese": "Đồng hồ", "phonetic": "/klɒk/", "categoryId": "no2", "image": "clock", "level": "A1"},
    { "id": 151, "english": "Close", "vietnamese": "Đóng", "phonetic": "/kləʊz/", "categoryId": "no9", "image": "close", "level": "A1"},
    { "id": 152, "english": "Clothes", "vietnamese": "Quần áo", "phonetic": "/kləʊðz/", "categoryId": "no2", "image": "clothes", "level": "A1"},
    { "id": 153, "english": "Club", "vietnamese": "Câu lạc bộ", "phonetic": "/klʌb/", "categoryId": "no7", "image": "club", "level": "A1"},
    { "id": 154, "english": "Coat", "vietnamese": "Áo khoác", "phonetic": "/kəʊt/", "categoryId": "no2", "image": "coat", "level": "A1"},
    { "id": 155, "english": "Coffee", "vietnamese": "Cà phê", "phonetic": "/ˈkɒfi/", "categoryId": "no3", "image": "coffee", "level": "A1"},
    { "id": 156, "english": "Cold", "vietnamese": "Lạnh", "phonetic": "/kəʊld/", "categoryId": "no8", "image": "cold", "level": "A1"},
    { "id": 157, "english": "College", "vietnamese": "Trường cao đẳng", "phonetic": "/ˈkɒlɪdʒ/", "categoryId": "no7", "image": "college", "level": "A1"},
    { "id": 158, "english": "Color", "vietnamese": "Màu sắc", "phonetic": "/ˈkʌlər/", "categoryId": "no10", "image": "color", "level": "A1"},
    { "id": 159, "english": "Come", "vietnamese": "Đến", "phonetic": "/kʌm/", "categoryId": "no9", "image": "come", "level": "A1"},
    { "id": 160, "english": "Common", "vietnamese": "Phổ biến", "phonetic": "/ˈkɒmən/", "categoryId": "no8", "image": "common", "level": "A1"},
    { "id": 161, "english": "Company", "vietnamese": "Công ty", "phonetic": "/ˈkʌmpəni/", "categoryId": "no7", "image": "company", "level": "A1"},
    { "id": 162, "english": "Compare", "vietnamese": "So sánh", "phonetic": "/kəmˈpeər/", "categoryId": "no9", "image": "compare", "level": "A1"},
    { "id": 163, "english": "Complete", "vietnamese": "Hoàn thành", "phonetic": "/kəmˈpliːt/", "categoryId": "no9", "image": "complete", "level": "A1"},
    { "id": 164, "english": "Computer", "vietnamese": "Máy tính", "phonetic": "/kəmˈpjuːtər/", "categoryId": "no2", "image": "computer", "level": "A1"},
    { "id": 165, "english": "Concert", "vietnamese": "Buổi hòa nhạc", "phonetic": "/ˈkɒnsət/", "categoryId": "no10", "image": "concert", "level": "A1"},
    { "id": 166, "english": "Conversation", "vietnamese": "Cuộc trò chuyện", "phonetic": "/ˌkɒnvəˈseɪʃn/", "categoryId": "no10", "image": "conversation", "level": "A1"},
    { "id": 167, "english": "Cook", "vietnamese": "Nấu ăn", "phonetic": "/kʊk/", "categoryId": "no9", "image": "cook", "level": "A1"},
    { "id": 168, "english": "Cooking", "vietnamese": "Việc nấu ăn", "phonetic": "/ˈkʊkɪŋ/", "categoryId": "no3", "image": "cooking", "level": "A1"},
    { "id": 169, "english": "Cool", "vietnamese": "Mát mẻ", "phonetic": "/kuːl/", "categoryId": "no8", "image": "cool", "level": "A1"},
    { "id": 170, "english": "Correct", "vietnamese": "Đúng", "phonetic": "/kəˈrekt/", "categoryId": "no8", "image": "correct", "level": "A1"},
    { "id": 171, "english": "Cost", "vietnamese": "Chi phí, giá", "phonetic": "/kɒst/", "categoryId": "no10", "image": "cost", "level": "A1"},
    { "id": 172, "english": "Could", "vietnamese": "Có thể", "phonetic": "/kʊd/", "categoryId": "no9", "image": "could", "level": "A1"},
    { "id": 173, "english": "Country", "vietnamese": "Đất nước", "phonetic": "/ˈkʌntri/", "categoryId": "no4", "image": "country", "level": "A1"},
    { "id": 174, "english": "Course", "vietnamese": "Khóa học", "phonetic": "/kɔːs/", "categoryId": "no7", "image": "course", "level": "A1"},
    { "id": 175, "english": "Cousin", "vietnamese": "Anh chị em họ", "phonetic": "/ˈkʌzn/", "categoryId": "no1", "image": "cousin", "level": "A1"},
    { "id": 176, "english": "Cow", "vietnamese": "Con bò", "phonetic": "/kaʊ/", "categoryId": "no5", "image": "https://upload.wikimedia.org/wikipedia/commons/3/38/Cow_bo_my.png", "level": "A1"},
    { "id": 177, "english": "Cream", "vietnamese": "Kem", "phonetic": "/kriːm/", "categoryId": "no3", "image": "cream", "level": "A1"},
    { "id": 178, "english": "Create", "vietnamese": "Tạo ra", "phonetic": "/kriˈeɪt/", "categoryId": "no9", "image": "create", "level": "A1"},
    { "id": 179, "english": "Culture", "vietnamese": "Văn hóa", "phonetic": "/ˈkʌltʃər/", "categoryId": "no10", "image": "culture", "level": "A1"},
    { "id": 180, "english": "Cup", "vietnamese": "Cái cốc", "phonetic": "/kʌp/", "categoryId": "no2", "image": "cup", "level": "A1"},
    { "id": 181, "english": "Cut", "vietnamese": "Cắt", "phonetic": "/kʌt/", "categoryId": "no9", "image": "cut", "level": "A1"},
    { "id": 182, "english": "Dad", "vietnamese": "Bố", "phonetic": "/dæd/", "categoryId": "no1", "image": "dad", "level": "A1"},
    { "id": 183, "english": "Dance", "vietnamese": "Nhảy", "phonetic": "/dɑːns/", "categoryId": "no9", "image": "dance", "level": "A1"},
    { "id": 184, "english": "Dancer", "vietnamese": "Vũ công", "phonetic": "/ˈdɑːnsər/", "categoryId": "no1", "image": "dancer", "level": "A1"},
    { "id": 185, "english": "Dancing", "vietnamese": "Sự nhảy múa", "phonetic": "/ˈdɑːnsɪŋ/", "categoryId": "no10", "image": "dancing", "level": "A1"},
    { "id": 186, "english": "Dangerous", "vietnamese": "Nguy hiểm", "phonetic": "/ˈdeɪndʒərəs/", "categoryId": "no8", "image": "dangerous", "level": "A1"},
    { "id": 187, "english": "Dark", "vietnamese": "Tối", "phonetic": "/dɑːk/", "categoryId": "no8", "image": "dark", "level": "A1"},
    { "id": 188, "english": "Date", "vietnamese": "Ngày", "phonetic": "/deɪt/", "categoryId": "no6", "image": "date", "level": "A1"},
    { "id": 189, "english": "Daughter", "vietnamese": "Con gái", "phonetic": "/ˈdɔːtər/", "categoryId": "no1", "image": "daughter", "level": "A1"},
    { "id": 190, "english": "Day", "vietnamese": "Ngày", "phonetic": "/deɪ/", "categoryId": "no6", "image": "day", "level": "A1"},
    { "id": 191, "english": "Dear", "vietnamese": "Thân mến", "phonetic": "/dɪər/", "categoryId": "no8", "image": "dear", "level": "A1"},
    { "id": 192, "english": "December", "vietnamese": "Tháng Mười Hai", "phonetic": "/dɪˈsembər/", "categoryId": "no6", "image": "december", "level": "A1"},
    { "id": 193, "english": "Decide", "vietnamese": "Quyết định", "phonetic": "/dɪˈsaɪd/", "categoryId": "no9", "image": "decide", "level": "A1"},
    { "id": 194, "english": "Delicious", "vietnamese": "Ngon", "phonetic": "/dɪˈlɪʃəs/", "categoryId": "no8", "image": "delicious", "level": "A1"},
    { "id": 195, "english": "Describe", "vietnamese": "Mô tả", "phonetic": "/dɪˈskraɪb/", "categoryId": "no9", "image": "describe", "level": "A1"},
    { "id": 196, "english": "Description", "vietnamese": "Sự mô tả", "phonetic": "/dɪˈskrɪpʃn/", "categoryId": "no10", "image": "description", "level": "A1"},
    { "id": 197, "english": "Design", "vietnamese": "Thiết kế", "phonetic": "/dɪˈzaɪn/", "categoryId": "no9", "image": "design", "level": "A1"},
    { "id": 198, "english": "Desk", "vietnamese": "Bàn làm việc", "phonetic": "/desk/", "categoryId": "no2", "image": "desk", "level": "A1"},
    { "id": 199, "english": "Detail", "vietnamese": "Chi tiết", "phonetic": "/ˈdiːteɪl/", "categoryId": "no10", "image": "detail", "level": "A1"},
    { "id": 200, "english": "Dialogue", "vietnamese": "Cuộc đối thoại", "phonetic": "/ˈdaɪəlɒɡ/", "categoryId": "no10", "image": "dialogue", "level": "A1"},
    { "id": 201, "english": "Dictionary", "vietnamese": "Từ điển", "phonetic": "/ˈdɪkʃənəri/", "categoryId": "no7", "image": "dictionary", "level": "A1"},
    { "id": 202, "english": "Die", "vietnamese": "Chết", "phonetic": "/daɪ/", "categoryId": "no9", "image": "die", "level": "A1"},
    { "id": 203, "english": "Diet", "vietnamese": "Chế độ ăn", "phonetic": "/ˈdaɪət/", "categoryId": "no3", "image": "diet", "level": "A1"},
    { "id": 204, "english": "Difference", "vietnamese": "Sự khác biệt", "phonetic": "/ˈdɪfrəns/", "categoryId": "no10", "image": "difference", "level": "A1"},
    { "id": 205, "english": "Different", "vietnamese": "Khác biệt", "phonetic": "/ˈdɪfrənt/", "categoryId": "no8", "image": "different", "level": "A1"},
    { "id": 206, "english": "Difficult", "vietnamese": "Khó khăn", "phonetic": "/ˈdɪfɪkəlt/", "categoryId": "no8", "image": "difficult", "level": "A1"},
    { "id": 207, "english": "Dinner", "vietnamese": "Bữa tối", "phonetic": "/ˈdɪnər/", "categoryId": "no3", "image": "dinner", "level": "A1"},
    { "id": 208, "english": "Dirty", "vietnamese": "Bẩn", "phonetic": "/ˈdɜːti/", "categoryId": "no8", "image": "dirty", "level": "A1"},
    { "id": 209, "english": "Discuss", "vietnamese": "Thảo luận", "phonetic": "/dɪˈskʌs/", "categoryId": "no9", "image": "discuss", "level": "A1"},
    { "id": 210, "english": "Dish", "vietnamese": "Món ăn, cái đĩa", "phonetic": "/dɪʃ/", "categoryId": "no3", "image": "dish", "level": "A1"},
    { "id": 211, "english": "Do", "vietnamese": "Làm", "phonetic": "/duː/", "categoryId": "no9", "image": "do", "level": "A1"},
    { "id": 212, "english": "Doctor", "vietnamese": "Bác sĩ", "phonetic": "/ˈdɒktər/", "categoryId": "no1", "image": "doctor", "level": "A1"},
    { "id": 213, "english": "Dog", "vietnamese": "Con chó", "phonetic": "/dɒɡ/", "categoryId": "no5", "image": "https://upload.wikimedia.org/wikipedia/commons/3/31/Dog_kute.png", "level": "A1"},
    { "id": 214, "english": "Dollar", "vietnamese": "Đô la", "phonetic": "/ˈdɒlər/", "categoryId": "no10", "image": "dollar", "level": "A1"},
    { "id": 215, "english": "Door", "vietnamese": "Cửa", "phonetic": "/dɔːr/", "categoryId": "no2", "image": "door", "level": "A1"},
    { "id": 216, "english": "Down", "vietnamese": "Xuống", "phonetic": "/daʊn/", "categoryId": "no10", "image": "down", "level": "A1"},
    { "id": 217, "english": "Downstairs", "vietnamese": "Tầng dưới", "phonetic": "/ˌdaʊnˈsteəz/", "categoryId": "no4", "image": "downstairs", "level": "A1"},
    { "id": 218, "english": "Draw", "vietnamese": "Vẽ", "phonetic": "/drɔː/", "categoryId": "no9", "image": "draw", "level": "A1"},
    { "id": 219, "english": "Dress", "vietnamese": "Váy", "phonetic": "/dres/", "categoryId": "no2", "image": "dress", "level": "A1"},
    { "id": 220, "english": "Drink", "vietnamese": "Uống", "phonetic": "/drɪŋk/", "categoryId": "no9", "image": "drink", "level": "A1"},
    { "id": 221, "english": "Drive", "vietnamese": "Lái xe", "phonetic": "/draɪv/", "categoryId": "no9", "image": "drive", "level": "A1"},
    { "id": 222, "english": "Driver", "vietnamese": "Tài xế", "phonetic": "/ˈdraɪvər/", "categoryId": "no1", "image": "driver", "level": "A1"},
    { "id": 223, "english": "During", "vietnamese": "Trong suốt", "phonetic": "/ˈdʒʊərɪŋ/", "categoryId": "no10", "image": "during", "level": "A1"},
    { "id": 224, "english": "DVD", "vietnamese": "Đĩa DVD", "phonetic": "/ˌdiːviːˈdiː/", "categoryId": "no2", "image": "dvd", "level": "A1"},
    { "id": 225, "english": "Each", "vietnamese": "Mỗi", "phonetic": "/iːtʃ/", "categoryId": "no10", "image": "each", "level": "A1"},
    { "id": 226, "english": "Ear", "vietnamese": "Tai", "phonetic": "/ɪər/", "categoryId": "no10", "image": "ear", "level": "A1"},
    { "id": 227, "english": "Early", "vietnamese": "Sớm", "phonetic": "/ˈɜːli/", "categoryId": "no6", "image": "early", "level": "A1"},
    { "id": 228, "english": "East", "vietnamese": "Phía Đông", "phonetic": "/iːst/", "categoryId": "no4", "image": "east", "level": "A1"},
    { "id": 229, "english": "Easy", "vietnamese": "Dễ dàng", "phonetic": "/ˈiːzi/", "categoryId": "no8", "image": "easy", "level": "A1"},
    { "id": 230, "english": "Eat", "vietnamese": "Ăn", "phonetic": "/iːt/", "categoryId": "no9", "image": "eat", "level": "A1"},
    { "id": 231, "english": "Egg", "vietnamese": "Trứng", "phonetic": "/eɡ/", "categoryId": "no3", "image": "egg", "level": "A1"},
    { "id": 232, "english": "Eight", "vietnamese": "Số tám", "phonetic": "/eɪt/", "categoryId": "no10", "image": "eight", "level": "A1"},
    { "id": 233, "english": "Eighteen", "vietnamese": "Số mười tám", "phonetic": "/ˌeɪˈtiːn/", "categoryId": "no10", "image": "eighteen", "level": "A1"},
    { "id": 234, "english": "Eighty", "vietnamese": "Số tám mươi", "phonetic": "/ˈeɪti/", "categoryId": "no10", "image": "eighty", "level": "A1"},
    { "id": 235, "english": "Elephant", "vietnamese": "Con voi", "phonetic": "/ˈelɪfənt/", "categoryId": "no5", "image": "https://upload.wikimedia.org/wikipedia/commons/d/d6/Elephant_voi_nau.png", "level": "A1"},
    { "id": 236, "english": "Eleven", "vietnamese": "Số mười một", "phonetic": "/ɪˈlevn/", "categoryId": "no10", "image": "eleven", "level": "A1"},
    { "id": 237, "english": "Else", "vietnamese": "Khác", "phonetic": "/els/", "categoryId": "no10", "image": "else", "level": "A1"},
    { "id": 238, "english": "Email", "vietnamese": "Thư điện tử", "phonetic": "/ˈiːmeɪl/", "categoryId": "no7", "image": "email", "level": "A1"},
    { "id": 239, "english": "End", "vietnamese": "Kết thúc", "phonetic": "/end/", "categoryId": "no9", "image": "end", "level": "A1"},
    { "id": 240, "english": "Enjoy", "vietnamese": "Thích thú", "phonetic": "/ɪnˈdʒɔɪ/", "categoryId": "no9", "image": "enjoy", "level": "A1"},
    { "id": 241, "english": "Enough", "vietnamese": "Đủ", "phonetic": "/ɪˈnʌf/", "categoryId": "no10", "image": "enough", "level": "A1"},
    { "id": 242, "english": "Euro", "vietnamese": "Đồng Euro", "phonetic": "/ˈjʊərəʊ/", "categoryId": "no10", "image": "euro", "level": "A1"},
    { "id": 243, "english": "Even", "vietnamese": "Thậm chí", "phonetic": "/ˈiːvn/", "categoryId": "no10", "image": "even", "level": "A1"},
    { "id": 244, "english": "Evening", "vietnamese": "Buổi tối", "phonetic": "/ˈiːvnɪŋ/", "categoryId": "no6", "image": "evening", "level": "A1"},
    { "id": 245, "english": "Event", "vietnamese": "Sự kiện", "phonetic": "/ɪˈvent/", "categoryId": "no10", "image": "event", "level": "A1"},
    { "id": 246, "english": "Ever", "vietnamese": "Đã từng", "phonetic": "/ˈevər/", "categoryId": "no6", "image": "ever", "level": "A1"},
    { "id": 247, "english": "Every", "vietnamese": "Mỗi", "phonetic": "/ˈevri/", "categoryId": "no10", "image": "every", "level": "A1"},
    { "id": 248, "english": "Everybody", "vietnamese": "Mọi người", "phonetic": "/ˈevribɒdi/", "categoryId": "no1", "image": "everybody", "level": "A1"},
    { "id": 249, "english": "Everyone", "vietnamese": "Mọi người", "phonetic": "/ˈevriwʌn/", "categoryId": "no1", "image": "everyone", "level": "A1"},
    { "id": 250, "english": "Everything", "vietnamese": "Mọi thứ", "phonetic": "/ˈevriθɪŋ/", "categoryId": "no10", "image": "everything", "level": "A1"},
    { "id": 251, "english": "Exam", "vietnamese": "Kỳ thi", "phonetic": "/ɪɡˈzæm/", "categoryId": "no7", "image": "exam", "level": "A1"},
    { "id": 252, "english": "Example", "vietnamese": "Ví dụ", "phonetic": "/ɪɡˈzɑːmpl/", "categoryId": "no7", "image": "example", "level": "A1"},
    { "id": 253, "english": "Excited", "vietnamese": "Hào hứng", "phonetic": "/ɪkˈsaɪtɪd/", "categoryId": "no8", "image": "excited", "level": "A1"},
    { "id": 254, "english": "Exciting", "vietnamese": "Thú vị", "phonetic": "/ɪkˈsaɪtɪŋ/", "categoryId": "no8", "image": "exciting", "level": "A1"},
    { "id": 255, "english": "Exercise", "vietnamese": "Bài tập", "phonetic": "/ˈeksəsaɪz/", "categoryId": "no7", "image": "exercise", "level": "A1"},
    { "id": 256, "english": "Expensive", "vietnamese": "Đắt", "phonetic": "/ɪkˈspensɪv/", "categoryId": "no8", "image": "expensive", "level": "A1"},
    { "id": 257, "english": "Explain", "vietnamese": "Giải thích", "phonetic": "/ɪkˈspleɪn/", "categoryId": "no9", "image": "explain", "level": "A1"},
    { "id": 258, "english": "Extra", "vietnamese": "Thêm", "phonetic": "/ˈekstrə/", "categoryId": "no8", "image": "extra", "level": "A1"},
    { "id": 259, "english": "Eye", "vietnamese": "Mắt", "phonetic": "/aɪ/", "categoryId": "no10", "image": "eye", "level": "A1"},
    { "id": 260, "english": "Face", "vietnamese": "Khuôn mặt", "phonetic": "/feɪs/", "categoryId": "no10", "image": "face", "level": "A1"},
    { "id": 261, "english": "Fact", "vietnamese": "Sự thật", "phonetic": "/fækt/", "categoryId": "no10", "image": "fact", "level": "A1"},
    { "id": 262, "english": "Fall", "vietnamese": "Ngã", "phonetic": "/fɔːl/", "categoryId": "no9", "image": "fall", "level": "A1"},
    { "id": 263, "english": "False", "vietnamese": "Sai", "phonetic": "/fɔːls/", "categoryId": "no8", "image": "false", "level": "A1"},
    { "id": 264, "english": "Family", "vietnamese": "Gia đình", "phonetic": "/ˈfæməli/", "categoryId": "no1", "image": "family", "level": "A1"},
    { "id": 265, "english": "Famous", "vietnamese": "Nổi tiếng", "phonetic": "/ˈfeɪməs/", "categoryId": "no8", "image": "famous", "level": "A1"},
    { "id": 266, "english": "Fantastic", "vietnamese": "Tuyệt vời", "phonetic": "/fænˈtæstɪk/", "categoryId": "no8", "image": "fantastic", "level": "A1"},
    { "id": 267, "english": "Far", "vietnamese": "Xa", "phonetic": "/fɑːr/", "categoryId": "no8", "image": "far", "level": "A1"},
    { "id": 268, "english": "Farm", "vietnamese": "Nông trại", "phonetic": "/fɑːm/", "categoryId": "no4", "image": "farm", "level": "A1"},
    { "id": 269, "english": "Farmer", "vietnamese": "Nông dân", "phonetic": "/ˈfɑːmər/", "categoryId": "no1", "image": "farmer", "level": "A1"},
    { "id": 270, "english": "Fast", "vietnamese": "Nhanh", "phonetic": "/fɑːst/", "categoryId": "no8", "image": "fast", "level": "A1"},
    { "id": 271, "english": "Fat", "vietnamese": "Béo", "phonetic": "/fæt/", "categoryId": "no8", "image": "fat", "level": "A1"},
    { "id": 272, "english": "Father", "vietnamese": "Bố", "phonetic": "/ˈfɑːðər/", "categoryId": "no1", "image": "father", "level": "A1"},
    { "id": 273, "english": "Favorite", "vietnamese": "Yêu thích", "phonetic": "/ˈfeɪvərɪt/", "categoryId": "no8", "image": "favorite", "level": "A1"},
    { "id": 274, "english": "February", "vietnamese": "Tháng Hai", "phonetic": "/ˈfebruəri/", "categoryId": "no6", "image": "february", "level": "A1"},
    { "id": 275, "english": "Feel", "vietnamese": "Cảm thấy", "phonetic": "/fiːl/", "categoryId": "no9", "image": "feel", "level": "A1"},
    { "id": 276, "english": "Feeling", "vietnamese": "Cảm giác", "phonetic": "/ˈfiːlɪŋ/", "categoryId": "no10", "image": "feeling", "level": "A1"},
    { "id": 277, "english": "Festival", "vietnamese": "Lễ hội", "phonetic": "/ˈfestɪvl/", "categoryId": "no10", "image": "festival", "level": "A1"},
    { "id": 278, "english": "Few", "vietnamese": "Một vài", "phonetic": "/fjuː/", "categoryId": "no10", "image": "few", "level": "A1"},
    { "id": 279, "english": "Fifteen", "vietnamese": "Số mười lăm", "phonetic": "/ˌfɪfˈtiːn/", "categoryId": "no10", "image": "fifteen", "level": "A1"},
    { "id": 280, "english": "Fifth", "vietnamese": "Thứ năm", "phonetic": "/fɪfθ/", "categoryId": "no10", "image": "fifth", "level": "A1"},
    { "id": 281, "english": "Fifty", "vietnamese": "Số năm mươi", "phonetic": "/ˈfɪfti/", "categoryId": "no10", "image": "fifty", "level": "A1"},
    { "id": 282, "english": "Fill", "vietnamese": "Làm đầy", "phonetic": "/fɪl/", "categoryId": "no9", "image": "fill", "level": "A1"},
    { "id": 283, "english": "Final", "vietnamese": "Cuối cùng", "phonetic": "/ˈfaɪnl/", "categoryId": "no8", "image": "final", "level": "A1"},
    { "id": 284, "english": "Find", "vietnamese": "Tìm thấy", "phonetic": "/faɪnd/", "categoryId": "no9", "image": "find", "level": "A1"},
    { "id": 285, "english": "Fine", "vietnamese": "Tốt, ổn", "phonetic": "/faɪn/", "categoryId": "no8", "image": "fine", "level": "A1"},
    { "id": 286, "english": "Finish", "vietnamese": "Kết thúc", "phonetic": "/ˈfɪnɪʃ/", "categoryId": "no9", "image": "finish", "level": "A1"},
    { "id": 287, "english": "Fire", "vietnamese": "Lửa", "phonetic": "/ˈfaɪər/", "categoryId": "no10", "image": "fire", "level": "A1"},
    { "id": 288, "english": "First", "vietnamese": "Đầu tiên", "phonetic": "/fɜːst/", "categoryId": "no10", "image": "first", "level": "A1"},
    { "id": 289, "english": "Fish", "vietnamese": "Con cá", "phonetic": "/fɪʃ/", "categoryId": "no5", "image": "https://upload.wikimedia.org/wikipedia/commons/9/94/Fish_ca_phi.png", "level": "A1"},
    { "id": 290, "english": "Five", "vietnamese": "Số năm", "phonetic": "/faɪv/", "categoryId": "no10", "image": "five", "level": "A1"},
    { "id": 291, "english": "Flight", "vietnamese": "Chuyến bay", "phonetic": "/flaɪt/", "categoryId": "no4", "image": "flight", "level": "A1"},
    { "id": 292, "english": "Floor", "vietnamese": "Sàn nhà", "phonetic": "/flɔːr/", "categoryId": "no4", "image": "floor", "level": "A1"},
    { "id": 293, "english": "Flower", "vietnamese": "Hoa", "phonetic": "/ˈflaʊər/", "categoryId": "no10", "image": "flower", "level": "A1"},
    { "id": 294, "english": "Fly", "vietnamese": "Bay", "phonetic": "/flaɪ/", "categoryId": "no9", "image": "fly", "level": "A1"},
    { "id": 295, "english": "Follow", "vietnamese": "Đi theo", "phonetic": "/ˈfɒləʊ/", "categoryId": "no9", "image": "follow", "level": "A1"},
    { "id": 296, "english": "Food", "vietnamese": "Thức ăn", "phonetic": "/fuːd/", "categoryId": "no3", "image": "food", "level": "A1"},
    { "id": 297, "english": "Foot", "vietnamese": "Bàn chân", "phonetic": "/fʊt/", "categoryId": "no10", "image": "foot", "level": "A1"},
    { "id": 298, "english": "Football", "vietnamese": "Bóng đá", "phonetic": "/ˈfʊtbɔːl/", "categoryId": "no10", "image": "football", "level": "A1"},
    { "id": 299, "english": "For", "vietnamese": "Cho", "phonetic": "/fɔːr/", "categoryId": "no10", "image": "for", "level": "A1"},
    { "id": 300, "english": "Forget", "vietnamese": "Quên", "phonetic": "/fəˈɡet/", "categoryId": "no9", "image": "forget", "level": "A1"},
    { "id": 301, "english": "Form", "vietnamese": "Hình thức", "phonetic": "/fɔːm/", "categoryId": "no10", "image": "form", "level": "A1"},
    { "id": 302, "english": "Forty", "vietnamese": "Số bốn mươi", "phonetic": "/ˈfɔːti/", "categoryId": "no10", "image": "forty", "level": "A1"},
    { "id": 303, "english": "Four", "vietnamese": "Số bốn", "phonetic": "/fɔːr/", "categoryId": "no10", "image": "four", "level": "A1"},
    { "id": 304, "english": "Fourteen", "vietnamese": "Số mười bốn", "phonetic": "/ˌfɔːˈtiːn/", "categoryId": "no10", "image": "fourteen", "level": "A1"},
    { "id": 305, "english": "Fourth", "vietnamese": "Thứ tư", "phonetic": "/fɔːθ/", "categoryId": "no10", "image": "fourth", "level": "A1"},
    { "id": 306, "english": "Free", "vietnamese": "Miễn phí", "phonetic": "/friː/", "categoryId": "no8", "image": "free", "level": "A1"},
    { "id": 307, "english": "Friday", "vietnamese": "Thứ Sáu", "phonetic": "/ˈfraɪdeɪ/", "categoryId": "no6", "image": "friday", "level": "A1"},
    { "id": 308, "english": "Friend", "vietnamese": "Bạn bè", "phonetic": "/frend/", "categoryId": "no1", "image": "friend", "level": "A1"},
    { "id": 309, "english": "Friendly", "vietnamese": "Thân thiện", "phonetic": "/ˈfrendli/", "categoryId": "no8", "image": "friendly", "level": "A1"},
    { "id": 310, "english": "From", "vietnamese": "Từ", "phonetic": "/frəm/", "categoryId": "no10", "image": "from", "level": "A1"},
    { "id": 311, "english": "Front", "vietnamese": "Phía trước", "phonetic": "/frʌnt/", "categoryId": "no10", "image": "front", "level": "A1"},
    { "id": 312, "english": "Fruit", "vietnamese": "Trái cây", "phonetic": "/fruːt/", "categoryId": "no3", "image": "fruit", "level": "A1"},
    { "id": 313, "english": "Full", "vietnamese": "Đầy", "phonetic": "/fʊl/", "categoryId": "no8", "image": "full", "level": "A1"},
    { "id": 314, "english": "Fun", "vietnamese": "Vui vẻ", "phonetic": "/fʌn/", "categoryId": "no10", "image": "fun", "level": "A1"},
    { "id": 315, "english": "Funny", "vietnamese": "Vui nhộn", "phonetic": "/ˈfʌni/", "categoryId": "no8", "image": "funny", "level": "A1"},
    { "id": 316, "english": "Future", "vietnamese": "Tương lai", "phonetic": "/ˈfjuːtʃər/", "categoryId": "no6", "image": "future", "level": "A1"},
    { "id": 317, "english": "Game", "vietnamese": "Trò chơi", "phonetic": "/ɡeɪm/", "categoryId": "no10", "image": "game", "level": "A1"},
    { "id": 318, "english": "Garden", "vietnamese": "Khu vườn", "phonetic": "/ˈɡɑːdn/", "categoryId": "no4", "image": "garden", "level": "A1"},
    { "id": 319, "english": "Geography", "vietnamese": "Địa lý", "phonetic": "/dʒiˈɒɡrəfi/", "categoryId": "no7", "image": "geography", "level": "A1"},
    { "id": 320, "english": "Get", "vietnamese": "Nhận", "phonetic": "/ɡet/", "categoryId": "no9", "image": "get", "level": "A1"},
    { "id": 321, "english": "Girl", "vietnamese": "Cô gái", "phonetic": "/ɡɜːl/", "categoryId": "no1", "image": "girl", "level": "A1"},
    { "id": 322, "english": "Girlfriend", "vietnamese": "Bạn gái", "phonetic": "/ˈɡɜːlfrend/", "categoryId": "no1", "image": "girlfriend", "level": "A1"},
    { "id": 323, "english": "Give", "vietnamese": "Cho", "phonetic": "/ɡɪv/", "categoryId": "no9", "image": "give", "level": "A1"},
    { "id": 324, "english": "Glass", "vietnamese": "Cái ly, kính", "phonetic": "/ɡlɑːs/", "categoryId": "no2", "image": "glass", "level": "A1"},
    { "id": 325, "english": "Go", "vietnamese": "Đi", "phonetic": "/ɡəʊ/", "categoryId": "no9", "image": "go", "level": "A1"},
    { "id": 326, "english": "Good", "vietnamese": "Tốt", "phonetic": "/ɡʊd/", "categoryId": "no8", "image": "good", "level": "A1"},
    { "id": 327, "english": "Goodbye", "vietnamese": "Tạm biệt", "phonetic": "/ˌɡʊdˈbaɪ/", "categoryId": "no10", "image": "goodbye", "level": "A1"},
    { "id": 328, "english": "Grandfather", "vietnamese": "Ông", "phonetic": "/ˈɡrænfɑːðər/", "categoryId": "no1", "image": "grandfather", "level": "A1"},
    { "id": 329, "english": "Grandmother", "vietnamese": "Bà", "phonetic": "/ˈɡrænmʌðər/", "categoryId": "no1", "image": "grandmother", "level": "A1"},
    { "id": 330, "english": "Grandparent", "vietnamese": "Ông bà", "phonetic": "/ˈɡrænpeərənt/", "categoryId": "no1", "image": "grandparent", "level": "A1"},
    { "id": 331, "english": "Gray", "vietnamese": "Màu xám", "phonetic": "/ɡreɪ/", "categoryId": "no10", "image": "gray", "level": "A1"},
    { "id": 332, "english": "Great", "vietnamese": "Tuyệt vời", "phonetic": "/ɡreɪt/", "categoryId": "no8", "image": "great", "level": "A1"},
    { "id": 333, "english": "Green", "vietnamese": "Màu xanh lá", "phonetic": "/ɡriːn/", "categoryId": "no10", "image": "green", "level": "A1"},
    { "id": 334, "english": "Group", "vietnamese": "Nhóm", "phonetic": "/ɡruːp/", "categoryId": "no10", "image": "group", "level": "A1"},
    { "id": 335, "english": "Grow", "vietnamese": "Phát triển", "phonetic": "/ɡrəʊ/", "categoryId": "no9", "image": "grow", "level": "A1"},
    { "id": 336, "english": "Guess", "vietnamese": "Đoán", "phonetic": "/ɡes/", "categoryId": "no9", "image": "guess", "level": "A1"},
    { "id": 337, "english": "Guitar", "vietnamese": "Đàn ghi-ta", "phonetic": "/ɡɪˈtɑːr/", "categoryId": "no2", "image": "guitar", "level": "A1"},
    { "id": 338, "english": "Gym", "vietnamese": "Phòng tập thể dục", "phonetic": "/dʒɪm/", "categoryId": "no4", "image": "gym", "level": "A1"},
    { "id": 339, "english": "Hair", "vietnamese": "Tóc", "phonetic": "/heər/", "categoryId": "no10", "image": "hair", "level": "A1"},
    { "id": 340, "english": "Half", "vietnamese": "Một nửa", "phonetic": "/hɑːf/", "categoryId": "no10", "image": "half", "level": "A1"},
    { "id": 341, "english": "Hand", "vietnamese": "Bàn tay", "phonetic": "/hænd/", "categoryId": "no10", "image": "hand", "level": "A1"},
    { "id": 342, "english": "Happen", "vietnamese": "Xảy ra", "phonetic": "/ˈhæpən/", "categoryId": "no9", "image": "happen", "level": "A1"},
    { "id": 343, "english": "Happy", "vietnamese": "Hạnh phúc", "phonetic": "/ˈhæpi/", "categoryId": "no8", "image": "happy", "level": "A1"},
    { "id": 344, "english": "Hard", "vietnamese": "Khó", "phonetic": "/hɑːd/", "categoryId": "no8", "image": "hard", "level": "A1"},
    { "id": 345, "english": "Hat", "vietnamese": "Mũ", "phonetic": "/hæt/", "categoryId": "no2", "image": "hat", "level": "A1"},
    { "id": 346, "english": "Hate", "vietnamese": "Ghét", "phonetic": "/heɪt/", "categoryId": "no9", "image": "hate", "level": "A1"},
    { "id": 347, "english": "Have", "vietnamese": "Có", "phonetic": "/hæv/", "categoryId": "no9", "image": "have", "level": "A1"},
    { "id": 348, "english": "He", "vietnamese": "Anh ấy", "phonetic": "/hiː/", "categoryId": "no1", "image": "he", "level": "A1"},
    { "id": 349, "english": "Head", "vietnamese": "Cái đầu", "phonetic": "/hed/", "categoryId": "no10", "image": "head", "level": "A1"},
    { "id": 350, "english": "Health", "vietnamese": "Sức khỏe", "phonetic": "/helθ/", "categoryId": "no10", "image": "health", "level": "A1"},
    { "id": 351, "english": "Healthy", "vietnamese": "Khỏe mạnh", "phonetic": "/ˈhelθi/", "categoryId": "no8", "image": "healthy", "level": "A1"},
    { "id": 352, "english": "Hear", "vietnamese": "Nghe", "phonetic": "/hɪər/", "categoryId": "no9", "image": "hear", "level": "A1"},
    { "id": 353, "english": "Hello", "vietnamese": "Xin chào", "phonetic": "/həˈləʊ/", "categoryId": "no10", "image": "hello", "level": "A1"},
    { "id": 354, "english": "Help", "vietnamese": "Giúp đỡ", "phonetic": "/help/", "categoryId": "no9", "image": "help", "level": "A1"},
    { "id": 355, "english": "Her", "vietnamese": "Của cô ấy", "phonetic": "/hɜːr/", "categoryId": "no10", "image": "her", "level": "A1"},
    { "id": 356, "english": "Here", "vietnamese": "Ở đây", "phonetic": "/hɪər/", "categoryId": "no10", "image": "here", "level": "A1"},
    { "id": 357, "english": "Hey", "vietnamese": "Này!", "phonetic": "/heɪ/", "categoryId": "no10", "image": "hey", "level": "A1"},
    { "id": 358, "english": "Hi", "vietnamese": "Chào", "phonetic": "/haɪ/", "categoryId": "no10", "image": "hi", "level": "A1"},
    { "id": 359, "english": "High", "vietnamese": "Cao", "phonetic": "/haɪ/", "categoryId": "no8", "image": "high", "level": "A1"},
    { "id": 360, "english": "Him", "vietnamese": "Anh ấy (tân ngữ)", "phonetic": "/hɪm/", "categoryId": "no1", "image": "him", "level": "A1"},
    { "id": 361, "english": "His", "vietnamese": "Của anh ấy", "phonetic": "/hɪz/", "categoryId": "no10", "image": "his", "level": "A1"},
    { "id": 362, "english": "History", "vietnamese": "Lịch sử", "phonetic": "/ˈhɪstri/", "categoryId": "no7", "image": "history", "level": "A1"},
    { "id": 363, "english": "Hobby", "vietnamese": "Sở thích", "phonetic": "/ˈhɒbi/", "categoryId": "no10", "image": "hobby", "level": "A1"},
    { "id": 364, "english": "Home", "vietnamese": "Nhà", "phonetic": "/həʊm/", "categoryId": "no4", "image": "home", "level": "A1"},
    { "id": 365, "english": "Homework", "vietnamese": "Bài tập về nhà", "phonetic": "/ˈhəʊmwɜːk/", "categoryId": "no7", "image": "homework", "level": "A1"},
    { "id": 366, "english": "Hope", "vietnamese": "Hy vọng", "phonetic": "/həʊp/", "categoryId": "no9", "image": "hope", "level": "A1"},
    { "id": 367, "english": "Horse", "vietnamese": "Con ngựa", "phonetic": "/hɔːs/", "categoryId": "no5", "image": "https://upload.wikimedia.org/wikipedia/commons/c/c3/Horse.png", "level": "A1"},
    { "id": 368, "english": "Hospital", "vietnamese": "Bệnh viện", "phonetic": "/ˈhɒspɪtl/", "categoryId": "no4", "image": "hospital", "level": "A1"},
    { "id": 369, "english": "Hot", "vietnamese": "Nóng", "phonetic": "/hɒt/", "categoryId": "no8", "image": "hot", "level": "A1"},
    { "id": 370, "english": "Hotel", "vietnamese": "Khách sạn", "phonetic": "/həʊˈtel/", "categoryId": "no4", "image": "hotel", "level": "A1"},
    { "id": 371, "english": "Hour", "vietnamese": "Giờ", "phonetic": "/ˈaʊər/", "categoryId": "no6", "image": "hour", "level": "A1"},
    { "id": 372, "english": "House", "vietnamese": "Ngôi nhà", "phonetic": "/haʊs/", "categoryId": "no4", "image": "house", "level": "A1"},
    { "id": 373, "english": "How", "vietnamese": "Như thế nào", "phonetic": "/haʊ/", "categoryId": "no10", "image": "how", "level": "A1"},
    { "id": 374, "english": "However", "vietnamese": "Tuy nhiên", "phonetic": "/haʊˈevər/", "categoryId": "no10", "image": "however", "level": "A1"},
    { "id": 375, "english": "Hundred", "vietnamese": "Một trăm", "phonetic": "/ˈhʌndrəd/", "categoryId": "no10", "image": "hundred", "level": "A1"},
    { "id": 376, "english": "Hungry", "vietnamese": "Đói", "phonetic": "/ˈhʌŋɡri/", "categoryId": "no8", "image": "hungry", "level": "A1"},
    { "id": 377, "english": "Husband", "vietnamese": "Chồng", "phonetic": "/ˈhʌzbənd/", "categoryId": "no1", "image": "husband", "level": "A1"},
    { "id": 378, "english": "I", "vietnamese": "Tôi", "phonetic": "/aɪ/", "categoryId": "no1", "image": "i", "level": "A1"},
    { "id": 379, "english": "Ice", "vietnamese": "Đá", "phonetic": "/aɪs/", "categoryId": "no3", "image": "ice", "level": "A1"},
    { "id": 380, "english": "Ice cream", "vietnamese": "Kem", "phonetic": "/ˌaɪs ˈkriːm/", "categoryId": "no3", "image": "ice_cream", "level": "A1"},
    { "id": 381, "english": "Idea", "vietnamese": "Ý tưởng", "phonetic": "/aɪˈdɪə/", "categoryId": "no10", "image": "idea", "level": "A1"},
    { "id": 382, "english": "If", "vietnamese": "Nếu", "phonetic": "/ɪf/", "categoryId": "no10", "image": "if", "level": "A1"},
    { "id": 383, "english": "Imagine", "vietnamese": "Tưởng tượng", "phonetic": "/ɪˈmædʒɪn/", "categoryId": "no9", "image": "imagine", "level": "A1"},
    { "id": 384, "english": "Important", "vietnamese": "Quan trọng", "phonetic": "/ɪmˈpɔːtnt/", "categoryId": "no8", "image": "important", "level": "A1"},
    { "id": 385, "english": "Improve", "vietnamese": "Cải thiện", "phonetic": "/ɪmˈpruːv/", "categoryId": "no9", "image": "improve", "level": "A1"},
    { "id": 386, "english": "In", "vietnamese": "Trong", "phonetic": "/ɪn/", "categoryId": "no10", "image": "in", "level": "A1"},
    { "id": 387, "english": "Include", "vietnamese": "Bao gồm", "phonetic": "/ɪnˈkluːd/", "categoryId": "no9", "image": "include", "level": "A1"},
    { "id": 388, "english": "Information", "vietnamese": "Thông tin", "phonetic": "/ˌɪnfəˈmeɪʃn/", "categoryId": "no10", "image": "information", "level": "A1"},
    { "id": 389, "english": "Interest", "vietnamese": "Sự quan tâm", "phonetic": "/ˈɪntrəst/", "categoryId": "no10", "image": "interest", "level": "A1"},
    { "id": 390, "english": "Interested", "vietnamese": "Quan tâm", "phonetic": "/ˈɪntrəstɪd/", "categoryId": "no8", "image": "interested", "level": "A1"},
    { "id": 391, "english": "Interesting", "vietnamese": "Thú vị", "phonetic": "/ˈɪntrəstɪŋ/", "categoryId": "no8", "image": "interesting", "level": "A1"},
    { "id": 392, "english": "Internet", "vietnamese": "Mạng Internet", "phonetic": "/ˈɪntənet/", "categoryId": "no7", "image": "internet", "level": "A1"},
    { "id": 393, "english": "Interview", "vietnamese": "Phỏng vấn", "phonetic": "/ˈɪntəvjuː/", "categoryId": "no7", "image": "interview", "level": "A1"},
    { "id": 394, "english": "Into", "vietnamese": "Vào trong", "phonetic": "/ˈɪntuː/", "categoryId": "no10", "image": "into", "level": "A1"},
    { "id": 395, "english": "Introduce", "vietnamese": "Giới thiệu", "phonetic": "/ˌɪntrəˈdjuːs/", "categoryId": "no9", "image": "introduce", "level": "A1"},
    { "id": 396, "english": "Island", "vietnamese": "Hòn đảo", "phonetic": "/ˈaɪlənd/", "categoryId": "no4", "image": "island", "level": "A1"},
    { "id": 397, "english": "It", "vietnamese": "Nó", "phonetic": "/ɪt/", "categoryId": "no10", "image": "it", "level": "A1"},
    { "id": 398, "english": "Its", "vietnamese": "Của nó", "phonetic": "/ɪts/", "categoryId": "no10", "image": "its", "level": "A1"},
    { "id": 399, "english": "Jacket", "vietnamese": "Áo khoác", "phonetic": "/ˈdʒækɪt/", "categoryId": "no2", "image": "jacket", "level": "A1"},
    { "id": 400, "english": "January", "vietnamese": "Tháng Một", "phonetic": "/ˈdʒænjuəri/", "categoryId": "no6", "image": "january", "level": "A1"},
    { "id": 401, "english": "Jeans", "vietnamese": "Quần jean", "phonetic": "/dʒiːnz/", "categoryId": "no2", "image": "jeans", "level": "A1"},
    { "id": 402, "english": "Job", "vietnamese": "Công việc", "phonetic": "/dʒɒb/", "categoryId": "no7", "image": "job", "level": "A1"},
    { "id": 403, "english": "Join", "vietnamese": "Tham gia", "phonetic": "/dʒɔɪn/", "categoryId": "no9", "image": "join", "level": "A1"},
    { "id": 404, "english": "Juice", "vietnamese": "Nước ép", "phonetic": "/dʒuːs/", "categoryId": "no3", "image": "juice", "level": "A1"},
    { "id": 405, "english": "July", "vietnamese": "Tháng Bảy", "phonetic": "/dʒuˈlaɪ/", "categoryId": "no6", "image": "july", "level": "A1"},
    { "id": 406, "english": "June", "vietnamese": "Tháng Sáu", "phonetic": "/dʒuːn/", "categoryId": "no6", "image": "june", "level": "A1"},
    { "id": 407, "english": "Just", "vietnamese": "Chỉ", "phonetic": "/dʒʌst/", "categoryId": "no10", "image": "just", "level": "A1"},
    { "id": 408, "english": "Keep", "vietnamese": "Giữ", "phonetic": "/kiːp/", "categoryId": "no9", "image": "keep", "level": "A1"},
    { "id": 409, "english": "Key", "vietnamese": "Chìa khóa", "phonetic": "/kiː/", "categoryId": "no2", "image": "key", "level": "A1"},
    { "id": 410, "english": "Kind", "vietnamese": "Loại", "phonetic": "/kaɪnd/", "categoryId": "no10", "image": "kind", "level": "A1"},
    { "id": 411, "english": "Kitchen", "vietnamese": "Nhà bếp", "phonetic": "/ˈkɪtʃɪn/", "categoryId": "no4", "image": "kitchen", "level": "A1"},
    { "id": 412, "english": "Know", "vietnamese": "Biết", "phonetic": "/nəʊ/", "categoryId": "no9", "image": "know", "level": "A1"},
    { "id": 413, "english": "Land", "vietnamese": "Đất liền", "phonetic": "/lænd/", "categoryId": "no4", "image": "land", "level": "A1"},
    { "id": 414, "english": "Language", "vietnamese": "Ngôn ngữ", "phonetic": "/ˈlæŋɡwɪdʒ/", "categoryId": "no7", "image": "language", "level": "A1"},
    { "id": 415, "english": "Large", "vietnamese": "Rộng lớn", "phonetic": "/lɑːdʒ/", "categoryId": "no8", "image": "large", "level": "A1"},
    { "id": 416, "english": "Last", "vietnamese": "Cuối cùng", "phonetic": "/lɑːst/", "categoryId": "no6", "image": "last", "level": "A1"},
    { "id": 417, "english": "Late", "vietnamese": "Muộn", "phonetic": "/leɪt/", "categoryId": "no6", "image": "late", "level": "A1"},
    { "id": 418, "english": "Later", "vietnamese": "Sau đó", "phonetic": "/ˈleɪtər/", "categoryId": "no6", "image": "later", "level": "A1"},
    { "id": 419, "english": "Laugh", "vietnamese": "Cười", "phonetic": "/lɑːf/", "categoryId": "no9", "image": "laugh", "level": "A1"},
    { "id": 420, "english": "Learn", "vietnamese": "Học", "phonetic": "/lɜːn/", "categoryId": "no9", "image": "learn", "level": "A1"},
    { "id": 421, "english": "Leave", "vietnamese": "Rời đi", "phonetic": "/liːv/", "categoryId": "no9", "image": "leave", "level": "A1"},
    { "id": 422, "english": "Left", "vietnamese": "Bên trái", "phonetic": "/left/", "categoryId": "no10", "image": "left", "level": "A1"},
    { "id": 423, "english": "Leg", "vietnamese": "Chân", "phonetic": "/leɡ/", "categoryId": "no10", "image": "leg", "level": "A1"},
    { "id": 424, "english": "Lesson", "vietnamese": "Bài học", "phonetic": "/ˈlesn/", "categoryId": "no7", "image": "lesson", "level": "A1"},
    { "id": 425, "english": "Let", "vietnamese": "Để, cho phép", "phonetic": "/let/", "categoryId": "no9", "image": "let", "level": "A1"},
    { "id": 426, "english": "Letter", "vietnamese": "Lá thư, chữ cái", "phonetic": "/ˈletər/", "categoryId": "no7", "image": "letter", "level": "A1"},
    { "id": 427, "english": "Library", "vietnamese": "Thư viện", "phonetic": "/ˈlaɪbrəri/", "categoryId": "no4", "image": "library", "level": "A1"},
    { "id": 428, "english": "Lie", "vietnamese": "Nằm", "phonetic": "/laɪ/", "categoryId": "no9", "image": "lie", "level": "A1"},
    { "id": 429, "english": "Life", "vietnamese": "Cuộc sống", "phonetic": "/laɪf/", "categoryId": "no10", "image": "life", "level": "A1"},
    { "id": 430, "english": "Light", "vietnamese": "Ánh sáng, nhẹ", "phonetic": "/laɪt/", "categoryId": "no10", "image": "light", "level": "A1"},
    { "id": 431, "english": "Like", "vietnamese": "Thích", "phonetic": "/laɪk/", "categoryId": "no9", "image": "like", "level": "A1"},
    { "id": 432, "english": "Line", "vietnamese": "Dòng kẻ", "phonetic": "/laɪn/", "categoryId": "no7", "image": "line", "level": "A1"},
    { "id": 433, "english": "Lion", "vietnamese": "Sư tử", "phonetic": "/ˈlaɪən/", "categoryId": "no5", "image": "https://upload.wikimedia.org/wikipedia/commons/0/08/Lion_su_tu.png", "level": "A1"},
    { "id": 434, "english": "List", "vietnamese": "Danh sách", "phonetic": "/lɪst/", "categoryId": "no7", "image": "list", "level": "A1"},
    { "id": 435, "english": "Listen", "vietnamese": "Nghe", "phonetic": "/ˈlɪsn/", "categoryId": "no9", "image": "listen", "level": "A1"},
    { "id": 436, "english": "Little", "vietnamese": "Nhỏ, ít", "phonetic": "/ˈlɪtl/", "categoryId": "no8", "image": "little", "level": "A1"},
    { "id": 437, "english": "Live", "vietnamese": "Sống", "phonetic": "/lɪv/", "categoryId": "no9", "image": "live", "level": "A1"},
    { "id": 438, "english": "Local", "vietnamese": "Địa phương", "phonetic": "/ˈləʊkl/", "categoryId": "no8", "image": "local", "level": "A1"},
    { "id": 439, "english": "Long", "vietnamese": "Dài", "phonetic": "/lɒŋ/", "categoryId": "no8", "image": "long", "level": "A1"},
    { "id": 440, "english": "Look", "vietnamese": "Nhìn", "phonetic": "/lʊk/", "categoryId": "no9", "image": "look", "level": "A1"},
    { "id": 441, "english": "Lose", "vietnamese": "Mất", "phonetic": "/luːz/", "categoryId": "no9", "image": "lose", "level": "A1"},
    { "id": 442, "english": "Lot", "vietnamese": "Nhiều", "phonetic": "/lɒt/", "categoryId": "no10", "image": "lot", "level": "A1"},
    { "id": 443, "english": "Love", "vietnamese": "Yêu", "phonetic": "/lʌv/", "categoryId": "no9", "image": "love", "level": "A1"},
    { "id": 444, "english": "Lunch", "vietnamese": "Bữa trưa", "phonetic": "/lʌntʃ/", "categoryId": "no3", "image": "lunch", "level": "A1"},
    { "id": 445, "english": "Machine", "vietnamese": "Máy móc", "phonetic": "/məˈʃiːn/", "categoryId": "no2", "image": "machine", "level": "A1"},
    { "id": 446, "english": "Magazine", "vietnamese": "Tạp chí", "phonetic": "/ˌmæɡəˈziːn/", "categoryId": "no7", "image": "magazine", "level": "A1"},
    { "id": 447, "english": "Main", "vietnamese": "Chính", "phonetic": "/meɪn/", "categoryId": "no8", "image": "main", "level": "A1"},
    { "id": 448, "english": "Make", "vietnamese": "Làm, chế tạo", "phonetic": "/meɪk/", "categoryId": "no9", "image": "make", "level": "A1"},
    { "id": 449, "english": "Mall", "vietnamese": "Trung tâm mua sắm", "phonetic": "/mɔːl/", "categoryId": "no4", "image": "mall", "level": "A1"},
    { "id": 450, "english": "Man", "vietnamese": "Người đàn ông", "phonetic": "/mæn/", "categoryId": "no1", "image": "man", "level": "A1"},
    { "id": 451, "english": "Many", "vietnamese": "Nhiều", "phonetic": "/ˈmeni/", "categoryId": "no10", "image": "many", "level": "A1"},
    { "id": 452, "english": "Map", "vietnamese": "Bản đồ", "phonetic": "/mæp/", "categoryId": "no2", "image": "map", "level": "A1"},
    { "id": 453, "english": "March", "vietnamese": "Tháng Ba", "phonetic": "/mɑːtʃ/", "categoryId": "no6", "image": "march", "level": "A1"},
    { "id": 454, "english": "Market", "vietnamese": "Chợ", "phonetic": "/ˈmɑːkɪt/", "categoryId": "no4", "image": "market", "level": "A1"},
    { "id": 455, "english": "Married", "vietnamese": "Đã kết hôn", "phonetic": "/ˈmærɪd/", "categoryId": "no8", "image": "married", "level": "A1"},
    { "id": 456, "english": "Match", "vietnamese": "Trận đấu, que diêm", "phonetic": "/mætʃ/", "categoryId": "no10", "image": "match", "level": "A1"},
    { "id": 457, "english": "May", "vietnamese": "Tháng Năm", "phonetic": "/meɪ/", "categoryId": "no6", "image": "may", "level": "A1"},
    { "id": 458, "english": "Maybe", "vietnamese": "Có lẽ", "phonetic": "/ˈmeɪbi/", "categoryId": "no10", "image": "maybe", "level": "A1"},
    { "id": 459, "english": "Me", "vietnamese": "Tôi (tân ngữ)", "phonetic": "/miː/", "categoryId": "no1", "image": "me", "level": "A1"},
    { "id": 460, "english": "Meal", "vietnamese": "Bữa ăn", "phonetic": "/miːl/", "categoryId": "no3", "image": "meal", "level": "A1"},
    { "id": 461, "english": "Mean", "vietnamese": "Có nghĩa là", "phonetic": "/miːn/", "categoryId": "no9", "image": "mean", "level": "A1"},
    { "id": 462, "english": "Meaning", "vietnamese": "Ý nghĩa", "phonetic": "/ˈmiːnɪŋ/", "categoryId": "no7", "image": "meaning", "level": "A1"},
    { "id": 463, "english": "Meat", "vietnamese": "Thịt", "phonetic": "/miːt/", "categoryId": "no3", "image": "meat", "level": "A1"},
    { "id": 464, "english": "Meet", "vietnamese": "Gặp", "phonetic": "/miːt/", "categoryId": "no9", "image": "meet", "level": "A1"},
    { "id": 465, "english": "Meeting", "vietnamese": "Cuộc họp", "phonetic": "/ˈmiːtɪŋ/", "categoryId": "no7", "image": "meeting", "level": "A1"},
    { "id": 466, "english": "Member", "vietnamese": "Thành viên", "phonetic": "/ˈmembər/", "categoryId": "no1", "image": "member", "level": "A1"},
    { "id": 467, "english": "Menu", "vietnamese": "Thực đơn", "phonetic": "/ˈmenjuː/", "categoryId": "no3", "image": "menu", "level": "A1"},
    { "id": 468, "english": "Message", "vietnamese": "Tin nhắn", "phonetic": "/ˈmesɪdʒ/", "categoryId": "no10", "image": "message", "level": "A1"},
    { "id": 469, "english": "Meter", "vietnamese": "Mét", "phonetic": "/ˈmiːtər/", "categoryId": "no10", "image": "meter", "level": "A1"},
    { "id": 470, "english": "Midnight", "vietnamese": "Nửa đêm", "phonetic": "/ˈmɪdnaɪt/", "categoryId": "no6", "image": "midnight", "level": "A1"},
    { "id": 471, "english": "Mile", "vietnamese": "Dặm", "phonetic": "/maɪl/", "categoryId": "no10", "image": "mile", "level": "A1"},
    { "id": 472, "english": "Milk", "vietnamese": "Sữa", "phonetic": "/mɪlk/", "categoryId": "no3", "image": "milk", "level": "A1"},
    { "id": 473, "english": "Million", "vietnamese": "Một triệu", "phonetic": "/ˈmɪljən/", "categoryId": "no10", "image": "million", "level": "A1"},
    { "id": 474, "english": "Minute", "vietnamese": "Phút", "phonetic": "/ˈmɪnɪt/", "categoryId": "no6", "image": "minute", "level": "A1"},
    { "id": 475, "english": "Miss", "vietnamese": "Bỏ lỡ, nhớ", "phonetic": "/mɪs/", "categoryId": "no9", "image": "miss", "level": "A1"},
    { "id": 476, "english": "Mistake", "vietnamese": "Lỗi", "phonetic": "/mɪˈsteɪk/", "categoryId": "no10", "image": "mistake", "level": "A1"},
    { "id": 477, "english": "Model", "vietnamese": "Mô hình", "phonetic": "/ˈmɒdl/", "categoryId": "no7", "image": "model", "level": "A1"},
    { "id": 478, "english": "Modern", "vietnamese": "Hiện đại", "phonetic": "/ˈmɒdn/", "categoryId": "no8", "image": "modern", "level": "A1"},
    { "id": 479, "english": "Mom", "vietnamese": "Mẹ", "phonetic": "/mɒm/", "categoryId": "no1", "image": "mom", "level": "A1"},
    { "id": 480, "english": "Moment", "vietnamese": "Khoảnh khắc", "phonetic": "/ˈməʊmənt/", "categoryId": "no6", "image": "moment", "level": "A1"},
    { "id": 481, "english": "Monday", "vietnamese": "Thứ Hai", "phonetic": "/ˈmʌndeɪ/", "categoryId": "no6", "image": "monday", "level": "A1"},
    { "id": 482, "english": "Money", "vietnamese": "Tiền", "phonetic": "/ˈmʌni/", "categoryId": "no10", "image": "money", "level": "A1"},
    { "id": 483, "english": "Month", "vietnamese": "Tháng", "phonetic": "/mʌnθ/", "categoryId": "no6", "image": "month", "level": "A1"},
    { "id": 484, "english": "More", "vietnamese": "Nhiều hơn", "phonetic": "/mɔːr/", "categoryId": "no10", "image": "more", "level": "A1"},
    { "id": 485, "english": "Morning", "vietnamese": "Buổi sáng", "phonetic": "/ˈmɔːnɪŋ/", "categoryId": "no6", "image": "morning", "level": "A1"},
    { "id": 486, "english": "Most", "vietnamese": "Nhất", "phonetic": "/məʊst/", "categoryId": "no10", "image": "most", "level": "A1"},
    { "id": 487, "english": "Mother", "vietnamese": "Mẹ", "phonetic": "/ˈmʌðər/", "categoryId": "no1", "image": "mother", "level": "A1"},
    { "id": 488, "english": "Mountain", "vietnamese": "Núi", "phonetic": "/ˈmaʊntɪn/", "categoryId": "no4", "image": "mountain", "level": "A1"},
    { "id": 489, "english": "Mouse", "vietnamese": "Con chuột", "phonetic": "/maʊs/", "categoryId": "no5", "image": "https://upload.wikimedia.org/wikipedia/commons/thumb/0/0d/%D0%9C%D1%8B%D1%88%D1%8C_2.jpg/640px-%D0%9C%D1%8B%D1%88%D1%8C_2.jpg", "level": "A1"},
    { "id": 490, "english": "Mouth", "vietnamese": "Miệng", "phonetic": "/maʊθ/", "categoryId": "no10", "image": "mouth", "level": "A1"},
    { "id": 491, "english": "Move", "vietnamese": "Di chuyển", "phonetic": "/muːv/", "categoryId": "no9", "image": "move", "level": "A1"},
    { "id": 492, "english": "Movie", "vietnamese": "Phim", "phonetic": "/ˈmuːvi/", "categoryId": "no10", "image": "movie", "level": "A1"},
    { "id": 493, "english": "Much", "vietnamese": "Nhiều", "phonetic": "/mʌtʃ/", "categoryId": "no10", "image": "much", "level": "A1"},
    { "id": 494, "english": "Museum", "vietnamese": "Bảo tàng", "phonetic": "/mjuˈziːəm/", "categoryId": "no4", "image": "museum", "level": "A1"},
    { "id": 495, "english": "Music", "vietnamese": "Âm nhạc", "phonetic": "/ˈmjuːzɪk/", "categoryId": "no10", "image": "music", "level": "A1"},
    { "id": 496, "english": "Must", "vietnamese": "Phải", "phonetic": "/mʌst/", "categoryId": "no9", "image": "must", "level": "A1"},
    { "id": 497, "english": "My", "vietnamese": "Của tôi", "phonetic": "/maɪ/", "categoryId": "no10", "image": "my", "level": "A1"},
    { "id": 498, "english": "Name", "vietnamese": "Tên", "phonetic": "/neɪm/", "categoryId": "no10", "image": "name", "level": "A1"},
    { "id": 499, "english": "Natural", "vietnamese": "Tự nhiên", "phonetic": "/ˈnætʃrəl/", "categoryId": "no8", "image": "natural", "level": "A1"},
    { "id": 500, "english": "Near", "vietnamese": "Gần", "phonetic": "/nɪər/", "categoryId": "no10", "image": "near", "level": "A1"},
    { "id": 501, "english": "Need", "vietnamese": "Cần", "phonetic": "/niːd/", "categoryId": "no9", "image": "need", "level": "A1"},
    { "id": 502, "english": "Negative", "vietnamese": "Tiêu cực", "phonetic": "/ˈneɡətɪv/", "categoryId": "no8", "image": "negative", "level": "A1"},
    { "id": 503, "english": "Neighbor", "vietnamese": "Hàng xóm", "phonetic": "/ˈneɪbər/", "categoryId": "no1", "image": "neighbor", "level": "A1"},
    { "id": 504, "english": "Neighborhood", "vietnamese": "Khu phố", "phonetic": "/ˈneɪbəhʊd/", "categoryId": "no4", "image": "neighborhood", "level": "A1"},
    { "id": 505, "english": "Never", "vietnamese": "Không bao giờ", "phonetic": "/ˈnevər/", "categoryId": "no6", "image": "never", "level": "A1"},
    { "id": 506, "english": "New", "vietnamese": "Mới", "phonetic": "/njuː/", "categoryId": "no8", "image": "new", "level": "A1"},
    { "id": 507, "english": "News", "vietnamese": "Tin tức", "phonetic": "/njuːz/", "categoryId": "no10", "image": "news", "level": "A1"},
    { "id": 508, "english": "Newspaper", "vietnamese": "Báo", "phonetic": "/ˈnjuːzpeɪpər/", "categoryId": "no7", "image": "newspaper", "level": "A1"},
    { "id": 509, "english": "Next", "vietnamese": "Tiếp theo", "phonetic": "/nekst/", "categoryId": "no10", "image": "next", "level": "A1"},
    { "id": 510, "english": "Next to", "vietnamese": "Bên cạnh", "phonetic": "/nekst tuː/", "categoryId": "no10", "image": "next_to", "level": "A1"},
    { "id": 511, "english": "Nice", "vietnamese": "Tốt, đẹp", "phonetic": "/naɪs/", "categoryId": "no8", "image": "nice", "level": "A1"},
    { "id": 512, "english": "Night", "vietnamese": "Ban đêm", "phonetic": "/naɪt/", "categoryId": "no6", "image": "night", "level": "A1"},
    { "id": 513, "english": "Nine", "vietnamese": "Số chín", "phonetic": "/naɪn/", "categoryId": "no10", "image": "nine", "level": "A1"},
    { "id": 514, "english": "Nineteen", "vietnamese": "Số mười chín", "phonetic": "/ˌnaɪnˈtiːn/", "categoryId": "no10", "image": "nineteen", "level": "A1"},
    { "id": 515, "english": "Ninety", "vietnamese": "Số chín mươi", "phonetic": "/ˈnaɪnti/", "categoryId": "no10", "image": "ninety", "level": "A1"},
    { "id": 516, "english": "No", "vietnamese": "Không", "phonetic": "/nəʊ/", "categoryId": "no10", "image": "no", "level": "A1"},
    { "id": 517, "english": "No one", "vietnamese": "Không ai", "phonetic": "/nəʊ wʌn/", "categoryId": "no1", "image": "no_one", "level": "A1"},
    { "id": 518, "english": "Nobody", "vietnamese": "Không ai", "phonetic": "/ˈnəʊbədi/", "categoryId": "no1", "image": "nobody", "level": "A1"},
    { "id": 519, "english": "North", "vietnamese": "Phía Bắc", "phonetic": "/nɔːθ/", "categoryId": "no4", "image": "north", "level": "A1"},
    { "id": 520, "english": "Nose", "vietnamese": "Mũi", "phonetic": "/nəʊz/", "categoryId": "no10", "image": "nose", "level": "A1"},
    { "id": 521, "english": "Not", "vietnamese": "Không", "phonetic": "/nɒt/", "categoryId": "no10", "image": "not", "level": "A1"},
    { "id": 522, "english": "Note", "vietnamese": "Ghi chú", "phonetic": "/nəʊt/", "categoryId": "no7", "image": "note", "level": "A1"},
    { "id": 523, "english": "Nothing", "vietnamese": "Không có gì", "phonetic": "/ˈnʌθɪŋ/", "categoryId": "no10", "image": "nothing", "level": "A1"},
    { "id": 524, "english": "November", "vietnamese": "Tháng Mười Một", "phonetic": "/nəʊˈvembər/", "categoryId": "no6", "image": "november", "level": "A1"},
    { "id": 525, "english": "Now", "vietnamese": "Bây giờ", "phonetic": "/naʊ/", "categoryId": "no6", "image": "now", "level": "A1"},
    { "id": 526, "english": "Number", "vietnamese": "Con số", "phonetic": "/ˈnʌmbər/", "categoryId": "no10", "image": "number", "level": "A1"},
    { "id": 527, "english": "Nurse", "vietnamese": "Y tá", "phonetic": "/nɜːs/", "categoryId": "no1", "image": "nurse", "level": "A1"},
    { "id": 528, "english": "Object", "vietnamese": "Đồ vật", "phonetic": "/ˈɒbdʒɪkt/", "categoryId": "no2", "image": "object", "level": "A1"},
    { "id": 529, "english": "O'clock", "vietnamese": "Giờ đúng", "phonetic": "/əˈklɒk/", "categoryId": "no6", "image": "oclock", "level": "A1"},
    { "id": 530, "english": "October", "vietnamese": "Tháng Mười", "phonetic": "/ɒkˈtəʊbər/", "categoryId": "no6", "image": "october", "level": "A1"},
    { "id": 531, "english": "Of", "vietnamese": "Của", "phonetic": "/əv/", "categoryId": "no10", "image": "of", "level": "A1"},
    { "id": 532, "english": "Off", "vietnamese": "Tắt", "phonetic": "/ɒf/", "categoryId": "no10", "image": "off", "level": "A1"},
    { "id": 533, "english": "Office", "vietnamese": "Văn phòng", "phonetic": "/ˈɒfɪs/", "categoryId": "no4", "image": "office", "level": "A1"},
    { "id": 534, "english": "Often", "vietnamese": "Thường xuyên", "phonetic": "/ˈɒfn/", "categoryId": "no6", "image": "often", "level": "A1"},
    { "id": 535, "english": "Oh", "vietnamese": "Ồ", "phonetic": "/əʊ/", "categoryId": "no10", "image": "oh", "level": "A1"},
    { "id": 536, "english": "OK", "vietnamese": "Được", "phonetic": "/ˌəʊˈkeɪ/", "categoryId": "no10", "image": "ok", "level": "A1"},
    { "id": 537, "english": "Old", "vietnamese": "Cũ, già", "phonetic": "/əʊld/", "categoryId": "no8", "image": "old", "level": "A1"},
    { "id": 538, "english": "On", "vietnamese": "Trên", "phonetic": "/ɒn/", "categoryId": "no10", "image": "on", "level": "A1"},
    { "id": 539, "english": "Once", "vietnamese": "Một lần", "phonetic": "/wʌns/", "categoryId": "no6", "image": "once", "level": "A1"},
    { "id": 540, "english": "One", "vietnamese": "Số một", "phonetic": "/wʌn/", "categoryId": "no10", "image": "one", "level": "A1"},
    { "id": 541, "english": "Onion", "vietnamese": "Hành tây", "phonetic": "/ˈʌnjən/", "categoryId": "no3", "image": "onion", "level": "A1"},
    { "id": 542, "english": "Online", "vietnamese": "Trực tuyến", "phonetic": "/ˌɒnˈlaɪn/", "categoryId": "no10", "image": "online", "level": "A1"},
    { "id": 543, "english": "Only", "vietnamese": "Chỉ", "phonetic": "/ˈəʊnli/", "categoryId": "no10", "image": "only", "level": "A1"},
    { "id": 544, "english": "Open", "vietnamese": "Mở", "phonetic": "/ˈəʊpən/", "categoryId": "no9", "image": "open", "level": "A1"},
    { "id": 545, "english": "Opinion", "vietnamese": "Ý kiến", "phonetic": "/əˈpɪnjən/", "categoryId": "no10", "image": "opinion", "level": "A1"},
    { "id": 546, "english": "Opposite", "vietnamese": "Đối diện", "phonetic": "/ˈɒpəzɪt/", "categoryId": "no10", "image": "opposite", "level": "A1"},
    { "id": 547, "english": "Or", "vietnamese": "Hoặc", "phonetic": "/ɔːr/", "categoryId": "no10", "image": "or", "level": "A1"},
    { "id": 548, "english": "Orange", "vietnamese": "Quả cam, màu cam", "phonetic": "/ˈɒrɪndʒ/", "categoryId": "no3", "image": "orange", "level": "A1"},
    { "id": 549, "english": "Order", "vietnamese": "Gọi món, ra lệnh", "phonetic": "/ˈɔːdər/", "categoryId": "no9", "image": "order", "level": "A1"},
    { "id": 550, "english": "Other", "vietnamese": "Khác", "phonetic": "/ˈʌðər/", "categoryId": "no10", "image": "other", "level": "A1"},
    { "id": 551, "english": "Our", "vietnamese": "Của chúng tôi", "phonetic": "/ˈaʊər/", "categoryId": "no10", "image": "our", "level": "A1"},
    { "id": 552, "english": "Out", "vietnamese": "Ngoài", "phonetic": "/aʊt/", "categoryId": "no10", "image": "out", "level": "A1"},
    { "id": 553, "english": "Over", "vietnamese": "Trên", "phonetic": "/ˈəʊvər/", "categoryId": "no10", "image": "over", "level": "A1"},
    { "id": 554, "english": "Own", "vietnamese": "Sở hữu", "phonetic": "/əʊn/", "categoryId": "no10", "image": "own", "level": "A1"},
    { "id": 555, "english": "Page", "vietnamese": "Trang", "phonetic": "/peɪdʒ/", "categoryId": "no7", "image": "page", "level": "A1"},
    { "id": 556, "english": "Paint", "vietnamese": "Sơn, vẽ", "phonetic": "/peɪnt/", "categoryId": "no9", "image": "paint", "level": "A1"},
    { "id": 557, "english": "Painting", "vietnamese": "Bức tranh", "phonetic": "/ˈpeɪntɪŋ/", "categoryId": "no7", "image": "painting", "level": "A1"},
    { "id": 558, "english": "Pair", "vietnamese": "Cặp, đôi", "phonetic": "/peər/", "categoryId": "no10", "image": "pair", "level": "A1"},
    { "id": 559, "english": "Pants", "vietnamese": "Quần", "phonetic": "/pænts/", "categoryId": "no2", "image": "pants", "level": "A1"},
    { "id": 560, "english": "Paper", "vietnamese": "Giấy", "phonetic": "/ˈpeɪpər/", "categoryId": "no2", "image": "paper", "level": "A1"},
    { "id": 561, "english": "Paragraph", "vietnamese": "Đoạn văn", "phonetic": "/ˈpærəɡrɑːf/", "categoryId": "no7", "image": "paragraph", "level": "A1"},
    { "id": 562, "english": "Parent", "vietnamese": "Cha mẹ", "phonetic": "/ˈpeərənt/", "categoryId": "no1", "image": "parent", "level": "A1"},
    { "id": 563, "english": "Park", "vietnamese": "Công viên", "phonetic": "/pɑːk/", "categoryId": "no4", "image": "park", "level": "A1"},
    { "id": 564, "english": "Part", "vietnamese": "Phần", "phonetic": "/pɑːt/", "categoryId": "no10", "image": "part", "level": "A1"},
    { "id": 565, "english": "Partner", "vietnamese": "Đối tác", "phonetic": "/ˈpɑːtnər/", "categoryId": "no1", "image": "partner", "level": "A1"},
    { "id": 566, "english": "Party", "vietnamese": "Bữa tiệc", "phonetic": "/ˈpɑːti/", "categoryId": "no10", "image": "party", "level": "A1"},
    { "id": 567, "english": "Passport", "vietnamese": "Hộ chiếu", "phonetic": "/ˈpɑːspɔːt/", "categoryId": "no2", "image": "passport", "level": "A1"},
    { "id": 568, "english": "Past", "vietnamese": "Quá khứ", "phonetic": "/pɑːst/", "categoryId": "no6", "image": "past", "level": "A1"},
    { "id": 569, "english": "Pay", "vietnamese": "Trả tiền", "phonetic": "/peɪ/", "categoryId": "no9", "image": "pay", "level": "A1"},
    { "id": 570, "english": "Pen", "vietnamese": "Bút", "phonetic": "/pen/", "categoryId": "no2", "image": "pen", "level": "A1"},
    { "id": 571, "english": "Pencil", "vietnamese": "Bút chì", "phonetic": "/ˈpensl/", "categoryId": "no2", "image": "pencil", "level": "A1"},
    { "id": 572, "english": "People", "vietnamese": "Người", "phonetic": "/ˈpiːpl/", "categoryId": "no1", "image": "people", "level": "A1"},
    { "id": 573, "english": "Pepper", "vietnamese": "Tiêu", "phonetic": "/ˈpepər/", "categoryId": "no3", "image": "pepper", "level": "A1"},
    { "id": 574, "english": "Perfect", "vietnamese": "Hoàn hảo", "phonetic": "/ˈpɜːfɪkt/", "categoryId": "no8", "image": "perfect", "level": "A1"},
    { "id": 575, "english": "Person", "vietnamese": "Người", "phonetic": "/ˈpɜːsn/", "categoryId": "no1", "image": "person", "level": "A1"},
    { "id": 576, "english": "Personal", "vietnamese": "Cá nhân", "phonetic": "/ˈpɜːsənl/", "categoryId": "no8", "image": "personal", "level": "A1"},
    { "id": 577, "english": "Phone", "vietnamese": "Điện thoại", "phonetic": "/fəʊn/", "categoryId": "no2", "image": "phone", "level": "A1"},
    { "id": 578, "english": "Photo", "vietnamese": "Ảnh", "phonetic": "/ˈfəʊtəʊ/", "categoryId": "no2", "image": "photo", "level": "A1"},
    { "id": 579, "english": "Photograph", "vietnamese": "Bức ảnh", "phonetic": "/ˈfəʊtəɡrɑːf/", "categoryId": "no2", "image": "photograph", "level": "A1"},
    { "id": 580, "english": "Phrase", "vietnamese": "Cụm từ", "phonetic": "/freɪz/", "categoryId": "no7", "image": "phrase", "level": "A1"},
    { "id": 581, "english": "Piano", "vietnamese": "Đàn piano", "phonetic": "/piˈænəʊ/", "categoryId": "no2", "image": "piano", "level": "A1"},
    { "id": 582, "english": "Picture", "vietnamese": "Bức tranh", "phonetic": "/ˈpɪktʃər/", "categoryId": "no2", "image": "picture", "level": "A1"},
    { "id": 583, "english": "Piece", "vietnamese": "Mảnh", "phonetic": "/piːs/", "categoryId": "no10", "image": "piece", "level": "A1"},
    { "id": 584, "english": "Pig", "vietnamese": "Con lợn", "phonetic": "/pɪɡ/", "categoryId": "no5", "image": "https://upload.wikimedia.org/wikipedia/commons/0/04/Pig_heo.png", "level": "A1"},
    { "id": 585, "english": "Pink", "vietnamese": "Màu hồng", "phonetic": "/pɪŋk/", "categoryId": "no10", "image": "pink", "level": "A1"},
    { "id": 586, "english": "Place", "vietnamese": "Nơi", "phonetic": "/pleɪs/", "categoryId": "no4", "image": "place", "level": "A1"},
    { "id": 587, "english": "Plan", "vietnamese": "Kế hoạch", "phonetic": "/plæn/", "categoryId": "no10", "image": "plan", "level": "A1"},
    { "id": 588, "english": "Plane", "vietnamese": "Máy bay", "phonetic": "/pleɪn/", "categoryId": "no4", "image": "plane", "level": "A1"},
    { "id": 589, "english": "Plant", "vietnamese": "Cây", "phonetic": "/plɑːnt/", "categoryId": "no10", "image": "plant", "level": "A1"},
    { "id": 590, "english": "Play", "vietnamese": "Chơi", "phonetic": "/pleɪ/", "categoryId": "no9", "image": "play", "level": "A1"},
    { "id": 591, "english": "Player", "vietnamese": "Người chơi", "phonetic": "/ˈpleɪər/", "categoryId": "no1", "image": "player", "level": "A1"},
    { "id": 592, "english": "Please", "vietnamese": "Vui lòng", "phonetic": "/pliːz/", "categoryId": "no10", "image": "please", "level": "A1"},
    { "id": 593, "english": "Point", "vietnamese": "Điểm", "phonetic": "/pɔɪnt/", "categoryId": "no10", "image": "point", "level": "A1"},
    { "id": 594, "english": "Police", "vietnamese": "Cảnh sát", "phonetic": "/pəˈliːs/", "categoryId": "no7", "image": "police", "level": "A1"},
    { "id": 595, "english": "Policeman", "vietnamese": "Cảnh sát (nam)", "phonetic": "/pəˈliːsmən/", "categoryId": "no1", "image": "policeman", "level": "A1"},
    { "id": 596, "english": "Pool", "vietnamese": "Bể bơi", "phonetic": "/puːl/", "categoryId": "no4", "image": "pool", "level": "A1"},
    { "id": 597, "english": "Poor", "vietnamese": "Nghèo", "phonetic": "/pɔːr/", "categoryId": "no8", "image": "poor", "level": "A1"},
    { "id": 598, "english": "Popular", "vietnamese": "Phổ biến", "phonetic": "/ˈpɒpjələr/", "categoryId": "no8", "image": "popular", "level": "A1"},
    { "id": 599, "english": "Positive", "vietnamese": "Tích cực", "phonetic": "/ˈpɒzətɪv/", "categoryId": "no8", "image": "positive", "level": "A1"},
    { "id": 600, "english": "Possible", "vietnamese": "Có thể", "phonetic": "/ˈpɒsəbl/", "categoryId": "no8", "image": "possible", "level": "A1"}
  ]
}
